{"ok":true,"type":"services","answer":"I offer a range of photography services â?? including Workshops, Camera sensor cleaning, Online lessons, RPS mentoring, Private lessons, Gift vouchers.","answer_markdown":"I offer a range of photography services â?? including Workshops, Camera sensor cleaning, Online lessons, RPS mentoring, Private lessons, Gift vouchers.","confidence":0.7,"sources":{"services":[{"id":257590,"url":"https://www.alanranger.com/photographic-workshops-near-me","kind":"event","title":"Photographic Workshops Near Me","description":"LANDSCAPE PHOTOGRAPHIC WORKSHOPS NEAR ME 2025 - 2026","date_start":null,"date_end":null,"location":null,"price":null,"price_currency":null,"availability":null,"sku":null,"provider":"Alan Ranger Photography","source_url":"https://www.alanranger.com/photographic-workshops-near-me","raw":{"name":"Alan Ranger Photography","@type":"LocalBusiness","image":"https://static1.squarespace.com/static/5013f4b2c4aaa4752ac69b17/t/6749dba3f5275a74ca88a3bd/1761580471344/","address":"45 Hathaway Road\nCoventry, England, CV4 9HW\nUnited Kingdom","@context":"http://schema.org","openingHours":"Mo 09:00-17:00, Tu 09:00-17:00, We 09:00-17:00, Th 09:00-17:00, Fr 09:00-17:00, Sa 09:00-17:00, Su 09:00-17:00","_csv_end_time":null,"_csv_start_time":null},"entity_hash":"af02d9f62092b020bd2e8ca561861798ca70a33c","last_seen":"2025-10-29T18:30:50.426+00:00","page_url":"https://www.alanranger.com/photographic-workshops-near-me","norm_title":"alan ranger photography","start_date":null,"csv_type":"landing_service_pages","csv_metadata_id":70629,"categories":null,"tags":null,"publish_date":null,"location_name":null,"location_address":null,"excerpt":null,"end_date":null,"start_time":null,"end_time":null,"location_city_state_zip":null,"image_url":null,"json_ld_data":null,"workflow_state":null,"participants":null,"experience_level":null,"equipment_needed":null,"time_schedule":null,"fitness_level":null,"what_to_bring":null,"course_duration":"in milliseconds","instructor_info":null,"availability_status":null,"meta_description":null,"csv_metadata":{"kind":"service","title":null}},{"id":257688,"url":"https://www.alanranger.com/photography-services-near-me/camera-sensor-clean","kind":"service","title":"Professional Digital DSLR Camera Sensor Clean | Coventry","description":"UK Landscape Photography Workshops, Beginners Courses and Private Lessons - Enhance your skill with Alan Ranger Photography - Qualified Tutor and Professional Photographer","date_start":null,"date_end":null,"location":null,"price":null,"price_currency":null,"availability":null,"sku":null,"provider":"Alan Ranger Photography","source_url":"https://www.alanranger.com/photography-services-near-me/camera-sensor-clean","raw":{"url":"https://www.alanranger.com","name":"Alan Ranger Photography","@type":"WebSite","image":"//images.squarespace-cdn.com/content/v1/5013f4b2c4aaa4752ac69b17/b859ad2b-1442-4595-b9a4-410c32299bf8/ALAN+RANGER+photography+LOGO+BLACK.+switched+small.png","@context":"http://schema.org","description":"<p class=\"\" style=\"white-space:pre-wrap;\">UK Landscape Photography Workshops,&nbsp;Beginners Courses and Private Lessons - Enhance your skill with Alan Ranger Photography - Qualified Tutor and Professional Photographer</p>"},"entity_hash":"12456203015a25e561b5aa5d0ece9e33390a8b4b","last_seen":"2025-10-29T18:30:48.63+00:00","page_url":"https://www.alanranger.com/photography-services-near-me/camera-sensor-clean","norm_title":"professional digital dslr camera sensor clean | coventry","start_date":null,"csv_type":"landing_service_pages","csv_metadata_id":70746,"categories":["photography-services"],"tags":["sensor clean"],"publish_date":"2014-07-26","location_name":null,"location_address":"Drop and collect - 45 Hathaway Road, Coventry, CV4 9HWDuration: 60 mins, but the camera is to be collected the following day unless expressly agreed soonerPlease bring a camera with an empty memory card and lens attachedFully charged battery (Important otherwise, I may not be able to clean the sensor)\n\n\n\n\n\n\n\n\n\n\n\n\n\n\n\n\n\n\n\n\n\n  \n  \n\n\n\n\t\t\t\t\t\t\t\t\t\t\t\t\t\t\t\t\t\t\t\t\t\t\t\t\t\t\t\t\t\t\t\t\t\n\t\t\t\n{\n  \"@context\": \"https://schema.org/\",\n  \"@type\": \"Product\",\n  \"name\": \"Professional Digital DSLR Camera Sensor Clean | Coventry\",\n  \"image\": \"https://images.squarespace-cdn.com/content/v1/5013f4b2c4aaa4752ac69b17/1522495201980-KD6BKH54J01HJR93XXR6/photography-support-Services-1.png https://images.squarespace-cdn.com/content/v1/5013f4b2c4aaa4752ac69b17/1706983612066-FCM4V2DFPEUGVDMQNA7I/Camera+Sensor+Clean.jpg\",\n  \"description\": \"style=\\\"white-space:pre-wrap;\\\">Get a camera sensor clean in Coventry . Sensor checked and cleaned using professional equipment, swabs | Full Frame and Cropped Sensors | 24hr Turnaround\",\n  \"url\": \"https://www.alanranger.com/photography-services-near-me/camera-sensor-clean\",\n  \"offers\": {\n    \"@type\": \"Offer\",\n    \"priceCurrency\": \"GBP\",\n    \"price\": 30.0,\n    \"availability\": \"http://schema.org/InStock\",\n    \"shippingDetails\": {\n      \"@type\": \"OfferShippingDetails\",\n      \"doesNotShip\": \"http://schema.org/True\",\n      \"shippingDestination\": {\n        \"@type\": \"DefinedRegion\",\n        \"addressCountry\": \"GB\"\n      }\n    },\n    \"hasMerchantReturnPolicy\": {\n      \"@type\": \"MerchantReturnPolicy\",\n      \"returnPolicyCategory\": \"http://schema.org/MerchantReturnFiniteReturnWindow\",\n      \"merchantReturnDays\": 28,\n      \"returnMethod\": \"http://schema.org/ReturnByMail\",\n      \"returnFees\": \"http://schema.org/FreeReturn\",\n      \"applicableCountry\": \"GB\",\n      \"refundType\": \"http://schema.org/FullRefund\"\n    }\n  }\n}\n\n    \n    \n\n    \n\n      \n\n    \n\n    \n\n  \n\n\n\ndocument.querySelector('.ProductItem-details .sqs-add-to-cart-button').classList.remove('sqs-editable-button');\n              \n            \n          \n\n        \n      \n\n      \n\n  \n\n    \n\n\n\n\n\n\n\n\n\n\n\n\n\n\n\n\n\n\n\n\n  \n  \n\n\n\n\n\n  \n    \n      Get Access to Free Online Course\n      Sign up with your email address to access the Academy 101 Foundation Photography Course\n    \n    \n      \n        \n          \n            \n          \n            \n              \n              \n              \n                \n                  \n                \n                  First Name\n                  \n                \n              \n                  \n                \n                  Last Name\n                  \n                \n              \n                \n              \n            \n          \n        \n        \n          \n            \n              Email Address\n              \n            \n          \n        \n          \n        \n      \n      \n        \n          \n          Join today\n          \n        \n      \n      \n        \n      \n    \n    We respect your privacy.\n    Thank you! You will receive an email to verify and confirm your subscription to receive updates.  Please ensure you click the confirm button in the email.\n    \n  \n\n\n\n    \n      \n\n        \n          \n            \n              \n                Alan Ranger Photography\n                45 Hathaway Road,\n                Coventry, England, CV4 9HW,\n                United Kingdom\n              \n            \n            \n              +44 781 701 7994\n              info@alanranger.com\n            \n          \n        \n\n        \n          \n            \n              Hours\n              Mon 9am - 5pm\n              Tue 9am - 5pm\n              Wed 9am - 5pm\n              Thu 9am - 5pm\n              Fri 9am - 5pm\n              Sat 9am - 5pm\n              Sun 9am - 5pm\n            \n          \n        \n\n      \n\n      \n\n      \n  \n\n    Contact UsHelp - Site MapFree Online Photography CourseOnline - Zoom LessonsPrivate LessonsPhoto WorkshopsGift VouchersPhotography TipsSchedule an appointment\n\n  \n\n    \n\n    \n\n\n  Proud to be a member of\n\n\n\n\n\n\n\n\n\n\n\n\n\n\n\n\n\n\n\n\n\n  \n  \n\n\n\n\n\n\n\n\n\n\n\n\n\n\n\n\n\n\n\n\n\n\n\n\n\n\n\n\n\n\n\n\n\n\n\n\n\n\n\n\n\n\n\n\n\n\n  \n\n    \n  \n    \n\n      \n\n      \n        \n          \n        \n        \n\n        \n          \n            \n          \n            \n                \n                \n                \n                \n                \n                \n                \n                \n\n            \n          \n        \n          \n        \n\n        \n      \n        \n      \n\n    \n  \n\n\n  \n\n\n\n\n\n\n\n\n\n\n\n\n\n\n\n\n\n\n\n\n\n\n\n\n\n\n\n\n\n\n\n\n\n\n\n\n\n\n\n\n\n\n\n\n\n  \n\n    \n  \n    \n\n      \n\n      \n        \n          \n        \n        \n\n        \n          \n            \n          \n            \n                \n                \n                \n                \n                \n                \n                \n                \n\n            \n          \n        \n          \n        \n\n        \n      \n        \n      \n\n    \n  \n\n\n  \n\n\n\n\n\n\n\n\n\n\n\n\n\n\n\n\n\n\n\n\n\n\n\n\n\n\n\n\n\n\n\n\n\n\n\n\n\n\n\n\n\n\n\n\n\n  \n\n    \n  \n    \n\n      \n\n      \n        \n          \n        \n        \n\n        \n          \n            \n          \n            \n                \n                \n                \n                \n                \n                \n                \n                \n\n            \n          \n        \n          \n        \n\n        \n      \n        \n      \n\n    \n  \n\n\n  \n\n\n\n\n\n  Copyright Â© 2008-2025 Â Alan Ranger All Rights Reserved.  The Legal Stuff\n\n\n\n\n\n\n\n\n\n\n\n\n\n\n\n\n\n\n\n\n\n  \n  \n\n\n\n\n\n\n\n\n  \n    #block-yui_3_17_2_1_1651564402332_6670 .social-icons-style-border .sqs-svg-icon--wrapper {\n      \n        box-shadow: 0 0 0 2px inset;\n      \n      border: none; \n    }\n  \n  \n    \n      \n        \n          \n          \n        \n      \n    \n      \n        \n          \n          \n        \n      \n    \n      \n        \n          \n          \n        \n      \n    \n      \n        \n          \n          \n        \n      \n    \n      \n        \n          \n          \n        \n      \n    \n  \n\n\n\n\n  (44) 781-7017994 | info@alanranger.com45 Hathaway Road, Coventry, West Midlands, CV4 9HW, United Kingdom\n\n\n\n\n\n\n\n\n\n\n\n\n\n\n\n\n\n\n\n\n\n  \n  \n\n\n\n\n\n  \n\n\n\n\n    \n\n    \n    \n\n    \n\n\n\n\n\n\n\n{\n  \"@context\": \"http://schema.org\",\n  \"@type\": \"Organization\",\n  \"url\": \"https://www.alanranger.com/\",\n  \"logo\": \"https://www.alanranger.com/photography-tuition-icons/6ku1oah790lqdsn401bkwetsaai29o\",\n  \"contactPoint\": [{\n    \"@type\": \"ContactPoint\",\n    \"telephone\": \"+44-781-701-7994\",\n    \"contactType\": \"customer service\"\n  }]\n}\n\n\n\n\n\n(function () {\n  const removeProductSchema = () => {\n    const scripts = document.querySelectorAll('script[type=\"application/ld+json\"]');\n\n    scripts.forEach((script) => {\n      try {\n        const json = JSON.parse(script.textContent);\n\n        if (\n          json['@type'] === 'Product' ||\n          (Array.isArray(json['@type']) && json['@type'].includes('Product'))\n        ) {\n          // Optional safety: only remove if there's no review/aggregateRating\n          const hasReviewData = json.review || json.aggregateRating;\n          if (!hasReviewData) {\n            script.remove();\n          }\n        }\n      } catch (e) {\n        // Ignore malformed scripts\n      }\n    });\n  };\n\n  // Run once on DOM ready\n  document.addEventListener(\"DOMContentLoaded\", removeProductSchema);\n\n  // Run continuously for any future injections\n  const observer = new MutationObserver(() => {\n    removeProductSchema();\n  });\n\n  observer.observe(document.body, {\n    childList: true,\n    subtree: true\n  });\n})();\n\n\n\n\n\n\n\n\n\n\n\n!function(){window.self===window.top||window.top.document.getElementById(\"lazy-summaries-admin\")||function(e,t,s,i,a){if(s.querySelector(\"#\"+t))i&&i(this);else{var n=document.createElement(\"script\");n.src=e+\"?cache=\"+((new Date).getTime()+\"\").substr(0,8),n.id=t,n.onload=function(){a&&this.remove(),i&&i(this)},s.appendChild(n)}}(\"https://assets.squarewebsites.org/lazy-summaries/lazy-summaries-admin.js\",\"lazy-summaries-admin\",window.top.document.getElementsByTagName(\"head\")[0])}();\n\n\n\n\n\n\n window.customRegisterInterestSettings = {\n        '.collection-type-events.view-item': {\n            render: '.eventitem-column-meta',\n            source: '/register-interest',\n            text: 'Register interest',\n            alignment: 'left',\n            size: 'small'\n        },\n   \t\t'.collection-type-products.view-item': {\n            render: '.ProductItem-summary .sqs-add-to-cart-button-wrapper|after',\n            source: '/register-interest-product',\n            text: 'Register interest',\n            alignment: 'left', \n            size: 'small'\n        },\n}\n\n\n\n\n\n\n!(function() {\n    function injectScript(file, id, node) {\n        if (node.querySelector('#' + id)) {\n            return;\n        };\n        var script = document.createElement(\"script\");\n        script.src = file + '?cache=' + (new Date().getTime() + '').substr(0, 13);\n        script.id = id;\n        node.appendChild(script);\n    }\n    if (window.self !== window.top) {\n        document.addEventListener('DOMContentLoaded', function() {\n            setTimeout(function() {\n                injectScript('https://assets.squarewebsites.org/utils/csv-sync/alan-ranger/csv-sync.min.js?time='+(new Date).getTime(), 'csv-collection-sync', window.top.document.getElementsByTagName(\"head\")[0]);\n            }, 200)\n        })\n    }\n})();\n\n\n\ndocument.addEventListener('DOMContentLoaded', function(){\n\tsetTimeout(function(){window.self!==window.top&&(window.top.document.getElementById(\"sqs-admin-hooks\")||window.top.Y.Get.js(\"https://assets.squarewebsites.org/utils/sqs-admin-hooks/sqs-admin-hooks.js?time=\"+(new Date).getTime(),function(e,o){e?console.log(\"Error loading Admin Hooks Script: \"+e[0].error,\"error\"):(console.log(\"Admin Hooks Init\"),o&&o.nodes[0].setAttribute(\"id\",\"sqs-admin-hooks\"))}),window.top.document.getElementById(\"sqs-admin-hooks-date-to-events\")||window.top.Y.Get.js(\"https://assets.squarewebsites.org/utils/sqs-admin-hooks/prepend-date-to-events-descr-hook/date-to-events-descr-hook.js?time=\"+(new Date).getTime(),function(e,o){e?console.log(\"Error loading Admin Hooks Script: \"+e[0].error,\"error\"):(console.log(\"Add date if same description Init\"),o&&o.nodes[0].setAttribute(\"id\",\"sqs-admin-hooks-date-to-events\"))}),window.top.document.getElementById(\"events-collection-sync\")||window.top.Y.Get.js(\"https://assets.squarewebsites.org/utils/events-ical/alanranger-com.min.js?time=\"+(new Date).getTime(),function(e,o){e?console.log(\"Error loading Admin Hooks Script: \"+e[0].error,\"error\"):(console.log(\"Sync Calendar Events\"),o&&o.nodes[0].setAttribute(\"id\",\"events-collection-sync\"))}))}, 200)  \n});\n\n\n\n\n\n\nwindow.collectionsSyncConfig = {\n  \t gallery: {\n            enabled: true,\n            onlyDefined: false,\n       \t\tmoreThan: 1,\n            general : {\n                saveBody: false,\n                saveExcerpt: false,\n                useLZS: false\n            }\n    },\n    events: {\n            enabled: false,\n            onlyDefined: false,\n            general : {\n                saveBody: false,\n                saveExcerpt: false,\n                useLZS: false\n            }\n      },\n      blog: {\n            enabled: false,\n            onlyDefined: false,\n            general : {\n                saveBody: false,\n                saveExcerpt: true,\n                useLZS: true\n            }\n        },\n  \t  products: {\n            enabled: false,\n            onlyDefined: false,\n            general : {\n                saveBody: false,\n                saveExcerpt: true,\n                useLZS: true\n            }\n        }\n  };\n  \n!function(){if(window.self!==window.top){var n,e,o,t,i,c;window.top.document.getElementById(\"collections-index-sync\")||(window.collectionsSyncConfig&&(window.top.collectionsSyncConfig=window.collectionsSyncConfig),n=\"https://assets.squarewebsites.org/utils/collections-indexes/collections-sync.min.js\",e=window.top.document.getElementsByTagName(\"head\")[0],o=\"collections-index-sync\",(c=document.createElement(\"script\")).id=o,c.src=n+\"?cache=\"+((new Date).getTime()+\"\").substr(0,7),c.async=!0,c.onload=function(){i&&this.remove(),t&&t(null,{nodes:[this]})},e.appendChild(c))}}();\n\n\n\n//Filter\nvar monthNames = [\"January\", \"February\", \"March\", \"April\", \"May\", \"June\", \"July\", \"August\", \"September\", \"October\", \"November\", \"December\"];\nvar locations = [\"batsford\",\"coventry\",\"cumbria\",\"devon\",\"dorset\",\"glencoe\",\"hope-valley\",\"kenilworth\",\"lake- district\",\"norfolk\",\"northumbria\",\"solihull\",\"somerset\",\"suffolk\",\"warwickshire\",\"worcestershire\",\"yorkshire\",\"wales\",\"residential\",\"ireland\"];\n\n\n.custom-filter-container.custom-filter-view-dropdowns .customFiltersWrapper .sqs-block {\n  max-width: 33.33%\n  }\n\nwindow.customFilterSettings = {\n    'targets': [{\n            container: '.sqs-events-collection-list, #block-yui_3_17_2_1_1521549855177_44542,#block-yui_3_17_2_1_1564902899455_5204,#collection-53d39321e4b009befdb652c8 .ProductList,#collection-5eb7c3a098232c36f5d347d5 .ProductList',\n            items: '.eventlist-event--upcoming, .summary-item, .ProductList-item',\n            settings: {\n                placeFiltersTo: '.placeFilters',\n                position: 'top',\n                showItemsCount: true,\n                customClasses: '',\n                align: 'center',\n                useHistory: true,\n                updateFilterOptions: {\n                    enabled: true,\n                    nonExistOptions: {\n                        hide: false,\n                        disable: false,\n                        disableHard: false\n                    },\n                    showOptionsCounters: true,\n                    optionsCounterWrap: '- ()',\n                },\n                //keepDropdownsOpen: true,\n                simpleFilter: {\n                    show: {\n                        effect: 'fade',\n                        transitionDuration: 300,\n                        stagger: 30\n                    },\n                    hide: {\n                        effect: 'fade',\n                        transitionDuration: 100,\n                        stagger: 18\n                    }\n                },\n                hooks: {\n                    beforeCreate: function(target) {\n                        if (location.pathname.indexOf('/photography-shop') > -1 || location.pathname.indexOf('/photography-services') > -1) {\n                            target.settings.filter = {\n                                category: false,\n                                tag: false,\n                                items: [{\n                                        name: 'Categories',\n                                        multiple: true,\n                                        getAttr: 'categories'\n                                    },\n                                    {\n                                        name: 'Tag',\n                                        multiple: true,\n                                        notAllowedOptions: locations,\n                                        getAttr: 'tags'\n                                    },\n                                    {\n                                        name: 'Location',\n                                        multiple: false,\n                                        allowedOptions: locations,\n                                        getAttr: 'tags'\n                                    },\n                                ]\n                            }\n                        }\n                        if (location.pathname.indexOf('workshops') > -1) {\n                            target.settings.filter = {\n                                category: false,\n                                tag: false,\n                                items: [{\n                                        name: 'Workshops Location',\n                                        multiple: false,\n                                        getAttr: function(el, data) {\n                                            if (data && data.location && data.location.addressTitle) {\n                                                return data.location.addressTitle;\n                                            }\n                                            return false;\n                                        }\n                                    },\n                                    {\n                                        name: 'Workshops Duration',\n                                        multiple: true,\n                                        getAttr: 'categories'\n                                    }, {\n                                        name: 'Workshops Year',\n                                        multiple: false,\n                                        getAttr: function(it, data) {\n                                            it = it._node || it;\n                                            var time = it.querySelector('[datetime]');\n                                            if (time) {\n                                                time = time.getAttribute('datetime').substr(0, 4);\n                                                return time;\n                                            } else if (data && data.startDate) {\n                                                return new Date(data.startDate).getFullYear()\n                                            }\n                                        }\n                                    },\n                                    {\n                                        name: 'Workshops Month',\n                                        multiple: false,\n                                        allowedOptions: monthNames,\n                                        sort: 'asAllowed',\n                                        getAttr: function(it, data) {\n                                            it = it._node || it;\n                                            var time = it.querySelector('[datetime]');\n                                            if (time) {\n                                                time = new Date(time.getAttribute('datetime')).toLocaleString('default', { month: 'long' });\n                                                return time;\n                                            } else if (data && data.startDate) {\n                                                return new Date(data.startDate).toLocaleString('default', { month: 'long' });\n                                            }\n                                        }\n                                    },\n                                    {\n                                        name: 'Tag',\n                                        multiple: true,\n                                        getAttr: 'tags'\n                                    }\n                                ]\n                            }\n                        }\n                        if (location.pathname.indexOf('course') > -1 || location.pathname.indexOf('classes') > -1) {\n                            target.settings.filter = {\n                                category: false,\n                                tag: false,\n                                items: [{\n                                        name: 'Courses Location',\n                                        multiple: true,\n                                        getAttr: function(el, data) {\n                                            if (data && data.location && data.location.addressTitle) {\n                                                return data.location.addressTitle;\n                                            }\n                                            return false;\n                                        }\n                                    },\n                                    {\n                                        name: 'Courses Categories',\n                                        multiple: true,\n                                        getAttr: 'categories'\n                                    }, {\n                                        name: 'Courses Year',\n                                        multiple: false,\n                                        getAttr: function(it, data) {\n                                            it = it._node || it;\n                                            var time = it.querySelector('[datetime]');\n                                            if (time) {\n                                                time = time.getAttribute('datetime').substr(0, 4);\n                                                return time;\n                                            } else if (data && data.startDate) {\n                                                return new Date(data.startDate).getFullYear()\n                                            }\n                                        }\n                                    }, {\n                                        name: 'Courses Month',\n                                        multiple: false,\n                                        allowedOptions: monthNames,\n                                        sort: 'asAllowed',\n                                        getAttr: function(it, data) {\n                                            it = it._node || it;\n                                            var time = it.querySelector('[datetime]');\n                                            if (time) {\n                                                time = new Date(time.getAttribute('datetime')).toLocaleString('default', { month: 'long' });\n                                                return time;\n                                            } else if (data && data.startDate) {\n                                                return new Date(data.startDate).toLocaleString('default', { month: 'long' });\n                                            }\n                                        }\n                                    }, {\n                                        name: 'Tag',\n                                        multiple: true,\n                                        getAttr: 'tags'\n                                    }\n                                ]\n                            }\n                        }\n                        if (location.pathname.indexOf('/photographic-workshops') > -1) {\n                            target.settings.position = 'top';\n                            //target.settings.customIndexUrl = '/workshops-events-custom-index';\n                        } else if (location.pathname.indexOf('/photography-classes') > -1) {\n                            target.settings.position = 'top';\n                            //target.settings.customIndexUrl = '/classes-events-custom-index';\n                        }\n                    }\n                },\n                sort: {\n                    items: [{\n                            name: 'A-Z',\n                            order: 'asc',\n                            sort: function(el, data) {\n                                if (data) {\n                                    return data.title;\n                                }\n                            }\n                        },\n                        {\n                            name: 'Z-A',\n                            order: 'desc',\n                            sort: function(el, data) {\n                                if (data) {\n                                    return data.title;\n                                }\n                            }\n                        },\n                        {\n                            name: 'Date',\n                            order: 'asc|desc',\n                            sort: function(el, data) {\n                                var result = 1;\n                                if (data && data.id) {\n                                    result = data.startDate;\n                                }\n                                return result;\n                            }\n                        }\n                    ]\n                }\n            }\n        },\n        {\n            container: '#collection-53836c32e4b05b1c55576880 .BlogList, #block-yui_3_17_2_1_1529137402624_4143',\n            items: '.hentry, .summary-item',\n            settings: {\n                //placeFiltersTo: '.collection-header',\n                position: 'top',\n                useSessionCache: false,\n                showItemsCount: true,\n                useHistory: true,\n                //keepDropdownsOpen: true,\n                updateFilterOptions: {\n                    enabled: true,\n                    nonExistOptions: {\n                        hide: false,\n                        disable: false,\n                        disableHard: false\n                    },\n                    showOptionsCounters: true,\n                    optionsCounterWrap: '- ()',\n                },\n                hooks: {\n                    beforeCreate: function(target) {\n                        if (window.top && window.top.Static && window.top.Static.IN_BACKEND) {\n                            target.noNeedCreate = true;\n                        }\n                    },\n                    beforeInit: function(filter) {\n                        //console.log(filter.target.settings)\n                        if (Y.one('body').hasClass('view-list')) {\n                            //filter.target.settings.customIndexUrl = '/blog-blog-custom-index';\n                        }\n                    },\n                    onInit: function(filter) {\n                        filter.target.settings.pagination.loadMoreButton.enabled = false;\n                    }\n                },\n                simpleFilter: {\n                    show: {\n                        effect: 'fade',\n                        transitionDuration: 300,\n                        stagger: 30\n                    },\n                    hide: {\n                        effect: 'fade',\n                        transitionDuration: 100,\n                        stagger: 18\n                    }\n                },\n                sort: {\n                    items: [{\n                        name: 'A-Z',\n                        order: 'asc',\n                        sort: function(el, data) {\n                            var title = '';\n                            if (data) {\n                                title = data.title;\n                            }\n                            return title;\n                        }\n                    }, {\n                        name: 'Z-A',\n                        order: 'desc',\n                        sort: function(el, data) {\n                            var title = '';\n                            if (data) {\n                                title = data.title;\n                            }\n                            return title;\n                        }\n                    }, {\n                        name: 'Date',\n                        order: 'asc|desc',\n                        sort: function(el, data) {\n                            var result = 1;\n                            if (data && data.id) {\n                                result = data.publishOn;\n                            }\n                            return result;\n                        }\n                    }]\n                },\n                pagination: {\n                    enabled: true,\n                    pageSize: 8,\n                    place: \"bottom\",\n                    showPrevNext: { //will show next/prev elements arrows\n                        enabled: true,\n                        //hideItems: true,\n                        next: 'Next', //next link text\n                        prev: 'Prev' //previous link text\n                    },\n                    loadMoreButton: {\n                        enabled: false\n                    }\n                },\n                filter: {\n                    category: false,\n                    tag: false,\n                    items: [{\n                        name: 'Category',\n                        multiple: true,\n                        getAttr: 'categories'\n                    }, {\n                        name: 'Tag',\n                        multiple: true,\n                        getAttr: 'tags'\n                    }]\n                }\n            }\n        }\n    ]\n};\n\n\n\n\n\n\n\n!function(){window.self===window.top||window.document.getElementById(\"sqstp-UI-theme-script\")||function(e,t,s,i,a){if(s.querySelector(\"#\"+t))i&&i(this);else{var n=document.createElement(\"script\");n.src=e+\"?cache=\"+((new Date).getTime()+\"\").substr(0,8),n.async=!0,n.id=t,n.onload=function(){a&&this.remove(),i&&i(this)},s.appendChild(n)}}(\"https://plugins.squarewebsites.org/sqstools-ext/themes/modern.min.js\",\"sqstp-UI-theme-script\",window.document.getElementsByTagName(\"head\")[0])}();\n\n\n\n\n\n\n\n$( \".reading-time\" ).insertBefore( \"h1.BlogItem-title\" );\n\n\n\n\n\n  var scrolled = 400; $(window).scroll(function() {\n    if ( $(window).scrollTop() > scrolled ) {\n      $('a.btt').fadeIn('slow');\n    } else {\n      $('a.btt').fadeOut('slow');\n    }\n  });\n\n\n  $('a.btt').click(function() {\n    $('html, body').animate({ scrollTop: 0 }, 700);\n    return false;\n  });\n\n\n\n\n$(document).ready(function () {\n    // Define the hover timeout duration in milliseconds\n    var hoverTimeoutDuration = 3000; // Example: 3000ms (3 seconds)\n\n    $('.Header-nav-folder-title[href^=\"/mega-\"]').each(function () {\n        var e = $(this).attr(\"href\").slice(6);\n        $(this).parent().addClass(\"mega-menu\");\n        var a = $(this).closest(\"header.Header\");\n        a.append(\"<div id=\" + e + ' class=\"mega-menu-item\"></div>');\n        $(\"#\" + e).load(\"/mega-menu-pages #mega-page-\" + e, function () {\n            window.Squarespace.initializeLayoutBlocks(Y, Y.one(\"#\" + e));\n            var imgs = document.querySelectorAll(\".mega-menu-item img[data-src]\");\n            for (var n = 0; n < imgs.length; n++) {\n                ImageLoader.load(imgs[n], { load: true, fill: true });\n                imgs[n].parentNode.className += \" loaded\";\n            }\n        });\n        var hoverTimeout;\n        // Function to start hover timeout\n        function startHoverTimeout() {\n            clearTimeout(hoverTimeout);\n            hoverTimeout = setTimeout(function () {\n                removeHoverFromAll();\n            }, hoverTimeoutDuration);\n        }\n        // Function to remove hover from all mega menus\n        function removeHoverFromAll() {\n            $('.mega-menu-item').removeClass('hover');\n            $('.mega-menu').removeClass('hover');\n        }\n        // Handle hover on the link's parent\n        $(this).parent().hover(\n            function () {\n                removeHoverFromAll(); // Remove hover from all other mega menus\n                a.find(\"#\" + e).addClass(\"hover\");\n                clearTimeout(hoverTimeout);\n                // Monitor mouse movement to reset hover timeout\n                $(document).on(\"mousemove.megaMenu\", function () {\n                    clearTimeout(hoverTimeout);\n                    startHoverTimeout();\n                });\n            },\n            function () {\n                startHoverTimeout();\n                $(document).off(\"mousemove.megaMenu\");\n            }\n        );\n        // Handle hover on the mega menu content\n        $(\"#\" + e).hover(\n            function () {\n                a.find(\"#\" + e).addClass(\"hover\");\n                clearTimeout(hoverTimeout);\n\n                // Monitor mouse movement to reset hover timeout\n                $(document).on(\"mousemove.megaMenuContent\", function () {\n                    clearTimeout(hoverTimeout);\n                    startHoverTimeout();\n                });\n            },\n            function () {\n                startHoverTimeout();\n                $(document).off(\"mousemove.megaMenuContent\");\n            }\n        );\n        // Detect hover on anything outside the mega menu or its link\n        $(\"body\").on(\"mouseenter\", \"","excerpt":"Get a camera sensor clean in Coventry . Sensor checked and cleaned using professional equipment, swabs | Full Frame and Cropped Sensors | 24hr Turnaround","end_date":null,"start_time":null,"end_time":null,"location_city_state_zip":null,"image_url":null,"json_ld_data":{"url":"https://www.alanranger.com/photography-services-near-me/camera-sensor-clean","name":"Professional Digital DSLR Camera Sensor Clean | Coventry","@type":"Product","image":"https://images.squarespace-cdn.com/content/v1/5013f4b2c4aaa4752ac69b17/1522495201980-KD6BKH54J01HJR93XXR6/photography-support-Services-1.png","offers":{"@type":"Offer","price":30,"availability":"http://schema.org/InStock","priceCurrency":"GBP","shippingDetails":{"@type":"OfferShippingDetails","doesNotShip":"http://schema.org/True","shippingDestination":{"@type":"DefinedRegion","addressCountry":"GB"}},"hasMerchantReturnPolicy":{"@type":"MerchantReturnPolicy","refundType":"http://schema.org/FullRefund","returnFees":"http://schema.org/FreeReturn","returnMethod":"http://schema.org/ReturnByMail","applicableCountry":"GB","merchantReturnDays":28,"returnPolicyCategory":"http://schema.org/MerchantReturnFiniteReturnWindow"}},"@context":"https://schema.org/","description":"Get a camera sensor clean in Coventry . Sensor checked and cleaned using professional equipment, swabs | Full Frame and Cropped Sensors | 24hr Turnaround"},"workflow_state":null,"participants":null,"experience_level":null,"equipment_needed":null,"time_schedule":null,"fitness_level":null,"what_to_bring":null,"course_duration":"in milliseconds","instructor_info":null,"availability_status":null,"meta_description":"Get a camera sensor clean in Coventry . Sensor checked and cleaned using professional equipment, swabs | Full Frame and Cropped Sensors | 24hr Turnaround","csv_metadata":{"kind":"service","title":null}},{"id":257704,"url":"https://www.alanranger.com/photo-workshops-uk","kind":"event","title":"Photo Workshops Uk","description":"PHOTO WORKSHOPS UK | LANDSCAPE PHOTOGRAPHY WORKSHOPS","date_start":null,"date_end":null,"location":null,"price":null,"price_currency":null,"availability":null,"sku":null,"provider":"Alan Ranger Photography","source_url":"https://www.alanranger.com/photo-workshops-uk","raw":{"name":"Alan Ranger Photography","@type":"LocalBusiness","image":"https://static1.squarespace.com/static/5013f4b2c4aaa4752ac69b17/t/6749dba3f5275a74ca88a3bd/1761580471344/","address":"45 Hathaway Road\nCoventry, England, CV4 9HW\nUnited Kingdom","@context":"http://schema.org","openingHours":"Mo 09:00-17:00, Tu 09:00-17:00, We 09:00-17:00, Th 09:00-17:00, Fr 09:00-17:00, Sa 09:00-17:00, Su 09:00-17:00","_csv_end_time":null,"_csv_start_time":null},"entity_hash":"9e0216828fc7f180bb0168df0d1dcbc31e7b1f76","last_seen":"2025-10-29T18:30:47.194+00:00","page_url":"https://www.alanranger.com/photo-workshops-uk","norm_title":"alan ranger photography","start_date":null,"csv_type":"landing_service_pages","csv_metadata_id":70631,"categories":null,"tags":null,"publish_date":null,"location_name":null,"location_address":null,"excerpt":null,"end_date":null,"start_time":null,"end_time":null,"location_city_state_zip":null,"image_url":null,"json_ld_data":null,"workflow_state":null,"participants":null,"experience_level":null,"equipment_needed":null,"time_schedule":null,"fitness_level":null,"what_to_bring":null,"course_duration":"in milliseconds","instructor_info":null,"availability_status":null,"meta_description":null,"csv_metadata":{"kind":"service","title":null}},{"id":244487,"url":"https://www.alanranger.com/photography-mentoring-online-assignments","kind":"service","title":"Photography Mentoring Online - Monthly Assignments","description":"UK Landscape Photography Workshops, Beginners Courses and Private Lessons - Enhance your skill with Alan Ranger Photography - Qualified Tutor and Professional Photographer","date_start":null,"date_end":null,"location":null,"price":null,"price_currency":null,"availability":null,"sku":null,"provider":"Alan Ranger Photography","source_url":"https://www.alanranger.com/photography-mentoring-online-assignments","raw":{"url":"https://www.alanranger.com","name":"Alan Ranger Photography","@type":"WebSite","image":"//images.squarespace-cdn.com/content/v1/5013f4b2c4aaa4752ac69b17/b859ad2b-1442-4595-b9a4-410c32299bf8/ALAN+RANGER+photography+LOGO+BLACK.+switched+small.png","@context":"http://schema.org","description":"<p class=\"\" style=\"white-space:pre-wrap;\">UK Landscape Photography Workshops,&nbsp;Beginners Courses and Private Lessons - Enhance your skill with Alan Ranger Photography - Qualified Tutor and Professional Photographer</p>"},"entity_hash":"330a86fe9b5f75e82670c1620f045d3b679eaa10","last_seen":"2025-10-29T17:53:41.231+00:00","page_url":"https://www.alanranger.com/photography-mentoring-online-assignments","norm_title":"photography mentoring online - monthly assignments","start_date":null,"csv_type":"landing_service_pages","csv_metadata_id":70600,"categories":null,"tags":null,"publish_date":null,"location_name":null,"location_address":".pathname.indexOf('/photography-services') > -1) {","excerpt":null,"end_date":null,"start_time":null,"end_time":null,"location_city_state_zip":null,"image_url":null,"json_ld_data":null,"workflow_state":null,"participants":null,"experience_level":null,"equipment_needed":"Equipment necessaryDigital CameraComputerInternet connection and Dropbox","time_schedule":"Online - Zoom","fitness_level":null,"what_to_bring":null,"course_duration":"in milliseconds","instructor_info":null,"availability_status":null,"meta_description":"Photography mentoring online sessions - Monthly Assignments to expand your skills and experience and help you grow and diversify your knowledge.  Join Today.","csv_metadata":{"kind":"service","title":null}},{"id":244506,"url":"https://www.alanranger.com/photography-workshops","kind":"service","title":"Best UK Outdoor Landscape Photography Workshops | Book Now","description":"UK Landscape Photography Workshops, Beginners Courses and Private Lessons - Enhance your skill with Alan Ranger Photography - Qualified Tutor and Professional Photographer","date_start":null,"date_end":null,"location":null,"price":null,"price_currency":null,"availability":null,"sku":null,"provider":"Alan Ranger Photography","source_url":"https://www.alanranger.com/photography-workshops","raw":{"url":"https://www.alanranger.com","name":"Alan Ranger Photography","@type":"WebSite","image":"//images.squarespace-cdn.com/content/v1/5013f4b2c4aaa4752ac69b17/b859ad2b-1442-4595-b9a4-410c32299bf8/ALAN+RANGER+photography+LOGO+BLACK.+switched+small.png","@context":"http://schema.org","description":"<p class=\"\" style=\"white-space:pre-wrap;\">UK Landscape Photography Workshops,&nbsp;Beginners Courses and Private Lessons - Enhance your skill with Alan Ranger Photography - Qualified Tutor and Professional Photographer</p>"},"entity_hash":"b78f7423d579473648a82aaf32211681488142ff","last_seen":"2025-10-29T17:53:37.585+00:00","page_url":"https://www.alanranger.com/photography-workshops","norm_title":"best uk outdoor landscape photography workshops | book now","start_date":null,"csv_type":"landing_service_pages","csv_metadata_id":70602,"categories":null,"tags":null,"publish_date":null,"location_name":null,"location_address":".","excerpt":null,"end_date":null,"start_time":null,"end_time":null,"location_city_state_zip":null,"image_url":null,"json_ld_data":null,"workflow_state":null,"participants":null,"experience_level":null,"equipment_needed":null,"time_schedule":"out duration in milliseconds","fitness_level":null,"what_to_bring":null,"course_duration":"in milliseconds","instructor_info":". Something that doesnâ??t always come hand in handâ?","availability_status":null,"meta_description":"Join our top-rated landscape photography workshops across the UK. Perfect for beginners and intermediates. Book now for expert tuition in stunning locations!","csv_metadata":{"kind":"service","title":null}},{"id":244565,"url":"https://www.alanranger.com/photography-lessons-online-121","kind":"service","title":"Learn Photography from Home | Photography Lessons Online","description":"UK Landscape Photography Workshops, Beginners Courses and Private Lessons - Enhance your skill with Alan Ranger Photography - Qualified Tutor and Professional Photographer","date_start":null,"date_end":null,"location":null,"price":null,"price_currency":null,"availability":null,"sku":null,"provider":"Alan Ranger Photography","source_url":"https://www.alanranger.com/photography-lessons-online-121","raw":{"url":"https://www.alanranger.com","name":"Alan Ranger Photography","@type":"WebSite","image":"//images.squarespace-cdn.com/content/v1/5013f4b2c4aaa4752ac69b17/b859ad2b-1442-4595-b9a4-410c32299bf8/ALAN+RANGER+photography+LOGO+BLACK.+switched+small.png","@context":"http://schema.org","description":"<p class=\"\" style=\"white-space:pre-wrap;\">UK Landscape Photography Workshops,&nbsp;Beginners Courses and Private Lessons - Enhance your skill with Alan Ranger Photography - Qualified Tutor and Professional Photographer</p>"},"entity_hash":"d00a51fd9f73a27fb6a2f5c0d91768cd4add219a","last_seen":"2025-10-29T17:53:37.328+00:00","page_url":"https://www.alanranger.com/photography-lessons-online-121","norm_title":"learn photography from home | photography lessons online","start_date":null,"csv_type":"landing_service_pages","csv_metadata_id":70598,"categories":null,"tags":null,"publish_date":null,"location_name":null,"location_address":".pathname.indexOf('/photography-services') > -1) {","excerpt":null,"end_date":null,"start_time":null,"end_time":null,"location_city_state_zip":null,"image_url":null,"json_ld_data":null,"workflow_state":null,"participants":null,"experience_level":null,"equipment_needed":null,"time_schedule":"Online - Zoom","fitness_level":null,"what_to_bring":null,"course_duration":"in milliseconds","instructor_info":null,"availability_status":".","meta_description":"Enhance Your Photography Skills with Zoom Photography Lessons Online. Learn Camera Settings and Photo Editing Techniques.  All on 1-2-1 Basis - Join Now!","csv_metadata":{"kind":"service","title":null}},{"id":244488,"url":"https://www.alanranger.com/photography-payment-plan","kind":"service","title":"Pick N Mix Photography Payment Plan - Tuition Packages","description":"UK Landscape Photography Workshops, Beginners Courses and Private Lessons - Enhance your skill with Alan Ranger Photography - Qualified Tutor and Professional Photographer","date_start":null,"date_end":null,"location":null,"price":null,"price_currency":null,"availability":null,"sku":null,"provider":"Alan Ranger Photography","source_url":"https://www.alanranger.com/photography-payment-plan","raw":{"url":"https://www.alanranger.com","name":"Alan Ranger Photography","@type":"WebSite","image":"//images.squarespace-cdn.com/content/v1/5013f4b2c4aaa4752ac69b17/b859ad2b-1442-4595-b9a4-410c32299bf8/ALAN+RANGER+photography+LOGO+BLACK.+switched+small.png","@context":"http://schema.org","description":"<p class=\"\" style=\"white-space:pre-wrap;\">UK Landscape Photography Workshops,&nbsp;Beginners Courses and Private Lessons - Enhance your skill with Alan Ranger Photography - Qualified Tutor and Professional Photographer</p>"},"entity_hash":"52794883ee48c9fc54f2c3b3220f3bcec6961610","last_seen":"2025-10-29T17:53:36.738+00:00","page_url":"https://www.alanranger.com/photography-payment-plan","norm_title":"pick n mix photography payment plan - tuition packages","start_date":null,"csv_type":"landing_service_pages","csv_metadata_id":70609,"categories":null,"tags":null,"publish_date":null,"location_name":null,"location_address":".pathname.indexOf('/photography-services') > -1) {","excerpt":null,"end_date":null,"start_time":null,"end_time":null,"location_city_state_zip":null,"image_url":null,"json_ld_data":null,"workflow_state":null,"participants":null,"experience_level":null,"equipment_needed":null,"time_schedule":"out duration in milliseconds","fitness_level":null,"what_to_bring":null,"course_duration":"in milliseconds","instructor_info":null,"availability_status":null,"meta_description":"Photography Payment Plan - Photography Tuition packages pick n mix - Choose courses, workshops or 1-2-1s The payment is interest free and spread over 12 months","csv_metadata":{"kind":"service","title":null}},{"id":244472,"url":"https://www.alanranger.com/private-photography-lessons","kind":"service","title":"Private Photography Lessons Near Me - Face to Face Coventry","description":"UK Landscape Photography Workshops, Beginners Courses and Private Lessons - Enhance your skill with Alan Ranger Photography - Qualified Tutor and Professional Photographer","date_start":null,"date_end":null,"location":null,"price":null,"price_currency":null,"availability":null,"sku":null,"provider":"Alan Ranger Photography","source_url":"https://www.alanranger.com/private-photography-lessons","raw":{"url":"https://www.alanranger.com","name":"Alan Ranger Photography","@type":"WebSite","image":"//images.squarespace-cdn.com/content/v1/5013f4b2c4aaa4752ac69b17/b859ad2b-1442-4595-b9a4-410c32299bf8/ALAN+RANGER+photography+LOGO+BLACK.+switched+small.png","@context":"http://schema.org","description":"<p class=\"\" style=\"white-space:pre-wrap;\">UK Landscape Photography Workshops,&nbsp;Beginners Courses and Private Lessons - Enhance your skill with Alan Ranger Photography - Qualified Tutor and Professional Photographer</p>"},"entity_hash":"937264ec9b50f46728f8ea0a6b9774d6db32d0d8","last_seen":"2025-10-29T17:53:36.671+00:00","page_url":"https://www.alanranger.com/private-photography-lessons","norm_title":"private photography lessons near me - face to face coventry","start_date":null,"csv_type":"landing_service_pages","csv_metadata_id":70599,"categories":null,"tags":null,"publish_date":null,"location_name":null,"location_address":"of your choice for your lesson.","excerpt":null,"end_date":null,"start_time":null,"end_time":null,"location_city_state_zip":null,"image_url":null,"json_ld_data":null,"workflow_state":null,"participants":null,"experience_level":null,"equipment_needed":null,"time_schedule":"Face-to-Face Coventry or your location","fitness_level":null,"what_to_bring":null,"course_duration":"in milliseconds","instructor_info":null,"availability_status":null,"meta_description":"Face to face private photography lessons near me in Coventry are taught at the pace of the individual. Combine theory and practice with a professional tutor","csv_metadata":{"kind":"service","title":null}},{"id":244470,"url":"https://www.alanranger.com/photography-gift-vouchers","kind":"service","title":"Photography Gift Vouchers - Buy Online Use against any event","description":"UK Landscape Photography Workshops, Beginners Courses and Private Lessons - Enhance your skill with Alan Ranger Photography - Qualified Tutor and Professional Photographer","date_start":null,"date_end":null,"location":null,"price":null,"price_currency":null,"availability":null,"sku":null,"provider":"Alan Ranger Photography","source_url":"https://www.alanranger.com/photography-gift-vouchers","raw":{"url":"https://www.alanranger.com","name":"Alan Ranger Photography","@type":"WebSite","image":"//images.squarespace-cdn.com/content/v1/5013f4b2c4aaa4752ac69b17/b859ad2b-1442-4595-b9a4-410c32299bf8/ALAN+RANGER+photography+LOGO+BLACK.+switched+small.png","@context":"http://schema.org","description":"<p class=\"\" style=\"white-space:pre-wrap;\">UK Landscape Photography Workshops,&nbsp;Beginners Courses and Private Lessons - Enhance your skill with Alan Ranger Photography - Qualified Tutor and Professional Photographer</p>"},"entity_hash":"dd450e09d22a5da0d5448665bcb1269275f28e63","last_seen":"2025-10-29T17:53:36.439+00:00","page_url":"https://www.alanranger.com/photography-gift-vouchers","norm_title":"photography gift vouchers - buy online use against any event","start_date":null,"csv_type":"landing_service_pages","csv_metadata_id":70606,"categories":null,"tags":null,"publish_date":null,"location_name":null,"location_address":".pathname.indexOf('/photography-services') > -1) {","excerpt":null,"end_date":null,"start_time":null,"end_time":null,"location_city_state_zip":null,"image_url":null,"json_ld_data":null,"workflow_state":null,"participants":null,"experience_level":null,"equipment_needed":null,"time_schedule":"out duration in milliseconds","fitness_level":null,"what_to_bring":null,"course_duration":"in milliseconds","instructor_info":null,"availability_status":null,"meta_description":"Photography Gift Vouchers - The Perfect Present for Any Enthusiast | Voucher Redeemable for Private Tuition, Lessons, Workshops, and More - Buy Online Today.","csv_metadata":{"kind":"service","title":null}},{"id":244537,"url":"https://www.alanranger.com/landscape-photography-workshops","kind":"service","title":"Landscape Photography Workshops UK â?? Inspiring Locations","description":"UK Landscape Photography Workshops, Beginners Courses and Private Lessons - Enhance your skill with Alan Ranger Photography - Qualified Tutor and Professional Photographer","date_start":null,"date_end":null,"location":null,"price":null,"price_currency":null,"availability":null,"sku":null,"provider":"Alan Ranger Photography","source_url":"https://www.alanranger.com/landscape-photography-workshops","raw":{"url":"https://www.alanranger.com","name":"Alan Ranger Photography","@type":"WebSite","image":"//images.squarespace-cdn.com/content/v1/5013f4b2c4aaa4752ac69b17/b859ad2b-1442-4595-b9a4-410c32299bf8/ALAN+RANGER+photography+LOGO+BLACK.+switched+small.png","@context":"http://schema.org","description":"<p class=\"\" style=\"white-space:pre-wrap;\">UK Landscape Photography Workshops,&nbsp;Beginners Courses and Private Lessons - Enhance your skill with Alan Ranger Photography - Qualified Tutor and Professional Photographer</p>"},"entity_hash":"e14f49155d68224cfd8b85ac8b10eee8cf3cbe5d","last_seen":"2025-10-29T17:53:24.51+00:00","page_url":"https://www.alanranger.com/landscape-photography-workshops","norm_title":"landscape photography workshops uk â?? inspiring locations","start_date":null,"csv_type":"landing_service_pages","csv_metadata_id":70603,"categories":null,"tags":null,"publish_date":null,"location_name":null,"location_address":"s2025 - 2026 Photo Workshops - 2.5 Hrs to 4 Hrs","excerpt":null,"end_date":null,"start_time":null,"end_time":null,"location_city_state_zip":null,"image_url":null,"json_ld_data":null,"workflow_state":null,"participants":null,"experience_level":null,"equipment_needed":null,"time_schedule":"out duration in milliseconds","fitness_level":null,"what_to_bring":null,"course_duration":"in milliseconds","instructor_info":null,"availability_status":null,"meta_description":"Master landscape photography in real UK locations. Small-group workshops with expert tutor Alan Ranger â?? practical, inspiring, and tailored to all levels.","csv_metadata":{"kind":"service","title":null}},{"id":244567,"url":"https://www.alanranger.com/free-online-photography-course","kind":"service","title":"Free Online Photography Course - Online Photography Academy","description":"UK Landscape Photography Workshops, Beginners Courses and Private Lessons - Enhance your skill with Alan Ranger Photography - Qualified Tutor and Professional Photographer","date_start":null,"date_end":null,"location":null,"price":null,"price_currency":null,"availability":null,"sku":null,"provider":"Alan Ranger Photography","source_url":"https://www.alanranger.com/free-online-photography-course","raw":{"url":"https://www.alanranger.com","name":"Alan Ranger Photography","@type":"WebSite","image":"//images.squarespace-cdn.com/content/v1/5013f4b2c4aaa4752ac69b17/b859ad2b-1442-4595-b9a4-410c32299bf8/ALAN+RANGER+photography+LOGO+BLACK.+switched+small.png","@context":"http://schema.org","description":"<p class=\"\" style=\"white-space:pre-wrap;\">UK Landscape Photography Workshops,&nbsp;Beginners Courses and Private Lessons - Enhance your skill with Alan Ranger Photography - Qualified Tutor and Professional Photographer</p>"},"entity_hash":"8893be56b37716f589d42d14cf8d4f64b2553c42","last_seen":"2025-10-29T17:53:24.377+00:00","page_url":"https://www.alanranger.com/free-online-photography-course","norm_title":"free online photography course - online photography academy","start_date":null,"csv_type":"landing_service_pages","csv_metadata_id":70591,"categories":null,"tags":null,"publish_date":null,"location_name":null,"location_address":"Where to find subjects and when to shoot","excerpt":null,"end_date":null,"start_time":null,"end_time":null,"location_city_state_zip":null,"image_url":null,"json_ld_data":null,"workflow_state":null,"participants":null,"experience_level":null,"equipment_needed":null,"time_schedule":"out duration in milliseconds","fitness_level":null,"what_to_bring":null,"course_duration":"in milliseconds","instructor_info":null,"availability_status":null,"meta_description":"Free online photography course from the Alan Ranger photography academy. 60 Modules - Camera settings, gear, composition, genres and photo practical exercises","csv_metadata":{"kind":"service","title":null}},{"id":244521,"url":"https://www.alanranger.com/beginners-photography-classes","kind":"service","title":"Beginners Photography Classes - 3 Weekly Evening Classes","description":"UK Landscape Photography Workshops, Beginners Courses and Private Lessons - Enhance your skill with Alan Ranger Photography - Qualified Tutor and Professional Photographer","date_start":null,"date_end":null,"location":null,"price":null,"price_currency":null,"availability":null,"sku":null,"provider":"Alan Ranger Photography","source_url":"https://www.alanranger.com/beginners-photography-classes","raw":{"url":"https://www.alanranger.com","name":"Alan Ranger Photography","@type":"WebSite","image":"//images.squarespace-cdn.com/content/v1/5013f4b2c4aaa4752ac69b17/b859ad2b-1442-4595-b9a4-410c32299bf8/ALAN+RANGER+photography+LOGO+BLACK.+switched+small.png","@context":"http://schema.org","description":"<p class=\"\" style=\"white-space:pre-wrap;\">UK Landscape Photography Workshops,&nbsp;Beginners Courses and Private Lessons - Enhance your skill with Alan Ranger Photography - Qualified Tutor and Professional Photographer</p>"},"entity_hash":"fa732234612b36294fd11899e53a76bc51b02c64","last_seen":"2025-10-29T17:53:24.157+00:00","page_url":"https://www.alanranger.com/beginners-photography-classes","norm_title":"beginners photography classes - 3 weekly evening classes","start_date":null,"csv_type":"landing_service_pages","csv_metadata_id":70595,"categories":null,"tags":null,"publish_date":null,"location_name":null,"location_address":"45 Hathaway Road, Tile Hill Village, Coventry, CV4 9HWParticipants: Max 4Time: 19:00 - 21:00Multi Course Start","excerpt":null,"end_date":null,"start_time":null,"end_time":null,"location_city_state_zip":null,"image_url":null,"json_ld_data":null,"workflow_state":null,"participants":"4","experience_level":"Beginner and Novice","equipment_needed":"You will need a DSLR or Mirrorless Camera with manual exposure modes.Alan will provide you with a course book covering all the topics for the course","time_schedule":"19:00 - 21:00Multi Course Start Dates: Beginners Photography Course3wks Mondays - Sep 8 - 22 Sep Coventry3wks Thursdays - Sep 11 - 25 Sep Coventry3wks Thursdays - Oct 2 - Oct 16 Coventry3wks Mondays - Oct 6 - Oct 20 Coventry3wks Mondays - Nov 3 - Nov 17 Coventry3wks Wednesdays - Nov 12 - Nov 26 Coventry3wks Tuesdays - Dec 2 - Dec 16 Coventry3wks Tuesdays - Jan 6 - Jan 20 Coventry3wks Wednesdays - Feb 4 - Feb 18 Coventry3wks Mondays - Mar 9 - Mar 23 CoventryExperience - Level: Beginner and NoviceThis beginners photography course is aimed at anyone with a digital camera wishing to get off auto exposure mode and learn about key camera settings and composition to make better photos.Equipment Needed:You will need a DSLR or Mirrorless Camera with manual exposure modes.Alan will provide you with a course book covering all the topics for the course\n\n          \n          \n            \n\n\n  \n    \n    \n  \n\n  \n    \n      \n        \n          \n            \n              \n                \n                  \n                    Dates:\n                  \n                  \n                    \n                      \n                        Select Dates\n                      \n                      \n                        3wks Mondays - Sep 8 - 22 Sep Coventry\n                      \n                        3wks Thursdays - Sep 11 - Sep 25 Coventry\n                      \n                        3wks Thursdays - Oct 2 - Oct 16 Coventry\n                      \n                        3wks Mondays - Oct 6 - Oct 20 Coventry\n                      \n                        3wks Mondays - Nov 3 - Nov 17 Coventry\n                      \n                        3wks Wednesdays - Nov 12 - Nov 26 Coventry\n                      \n                        3wks Tuesdays - Dec 2 - Dec 16 Coventry\n                      \n                        3wks Tuesdays - Jan 6 - Jan 20 Coventry\n                      \n                        3wks Wednesdays - Feb 4 - Feb 18 Coventry\n                      \n                        3wks Mondays - Mar 9 - Mar 23 Coventry\n                      \n                    \n                    \n                      \n                      \n                    \n                    \n                      \n                        \n                      \n                    \n                  \n                \n              \n            \n          \n        \n      \n    \n  \n\n\n            \n              \n                \n\n  \n\n\n\n  \n    \n      \n        \n          \n            \n              \n            \n          \n        \n        \n        \n          \n            \n              \n            \n          \n        \n      \n      \n        \n        \n      \n    \n  \n\n\n\n\n              \n              \n\n\n  \n    \n      \n        \n          Book\n        \n      \n      \n      \n    \n  \n\n\n            \n            \n\n\n  \n    \n  \n\n  \n    \n  \n    \n  \n    \n  \n    \n  \n    \n  \n    \n      \n        Only 4 available\n      \n    \n  \n    \n      \n        Only 4 available\n      \n    \n  \n    \n      \n        Only 4 available\n      \n    \n  \n    \n      \n        Only 4 available\n      \n    \n  \n    \n      \n        Only 4 available\n      \n    \n  \n\n\n          \n        \n      \n    \n  \n  \n\n\ndocument.querySelector('[data-definition-name=\"website.components.product\"] .product-block').classList.add('is-first-product-block');\n\n\n\n\n  Beginners Photography Classes - Course Structure and ContentOur photography course for beginners consists of three weekly evening sessions, each spanning two hours. Whether you opt for the Monday, Tuesday, Wednesday, or Thursday slot, you'll have the flexibility to accommodate the course into your schedule. \n\n\n\n\n\n\n\n\n\n\n\n\n\n\n\n\n\n\n\n\n\n  \n  \n\n\n\nÂ \n\n\n\n\n\n\n\n\n\n\n\n\n\n\n\n\n\n\n\n\n  \n  \n\n\n\n\n\n\n  \n    \n\n      \n        \n          \n        \n      \n\n      \n        \n          \n            Week 1 - Get off auto\n          \n          \n            \n              \n                \n                \n              \n            \n          \n        \n      \n      \n        \n          Wk 1 Get Off Auto - Beginners Photography ClassesIn the inaugural week of our digital photography course, you'll dive into the essentials of photography, learning how to transition from automatic modes to manual control of your camera settings. Explore the photographic workflow, comprehend the exposure triangle (aperture, ISO, and shutter speed), and uncover composition techniques to enhance your images in our basic photography courses.\n        \n      \n\n      \n        \n      \n\n    \n  \n    \n\n      \n        \n      \n\n      \n        \n          \n            Week 2 - Exposure\n          \n          \n            \n              \n                \n                \n              \n            \n          \n        \n      \n      \n        \n          Week 2: Exposure - Beginners Photography ClassesBuilding upon your knowledge from Week 1 of our photography course, Week 2 hones in on exposure. Revisit exposure concepts, learn about metering, histograms, and exposure compensation in our course. Engage in practical exercises and assignments to refine your exposure skills.\n        \n      \n\n      \n        \n      \n\n    \n  \n    \n\n      \n        \n      \n\n      \n        \n          \n            Week 3 - Camera Settings\n          \n          \n            \n              \n                \n                \n              \n            \n          \n        \n      \n      \n        \n          Week 3: Essential Camera Settings - Beginners Photography ClassesDelve deeper into the critical camera settings that can revolutionize your images in our photography course for beginners. Explore focusing techniques, depth of field, and white balance. Gain a more profound understanding of stops, dynamic range, and bracketing to capture the perfect shot.\n        \n      \n\n      \n        \n      \n\n    \n  \n\nÂ \n\n\n  Throughout this Beginners Photography Classes, you'll have the chance to complete practical assignments, allowing you to apply your newly acquired skills and receive feedback from the tutor. This hands-on approach in our course will reinforce your learning and help you evolve as a photographer in our beginner photography classes.You will need a DSLR camera, with any lens as you work through the different camera modes to transition you to manual exposure and working with the adjustments required in natural light.\n\n\n\n\n\n\n\n\n\n\n\n\n\n\n\n\n\n\n\n\n\n  \n  \n\n\n\nÂ \n\n\n  In Coventry 7 PM to 9 PM - Multiple Start Dates45 Hathaway Road, Tile Hill Village, Coventry, CV4 9HW\n\n\n\n\n\n\n\n\n\n\n\n\n\n\n\n\n\n\n\n\n\n  \n  \n\n\n\nÂ Â \n\n\n\n\n\n\n\n\n\n\n\n\n\n\n\n\n\n\n\n\n  \n  \n\n\n\n\n\n\n  \n    \n\n      \n        \n          \n        \n      \n\n      \n        \n          \n            [equipment-icon] What camera do I need for this course?\n          \n          \n            \n              \n                \n                \n              \n            \n          \n        \n      \n      \n        \n          Any DSLR or Mirrorless digital camera.   It doesnâ??t matter how old it is as long as it has the option to switch exposure modes between, Aperture, Shutter and Manual Exposure.I am happy to advise on models if you are looking to buy something but only after you have booked a place on my course or a 1-2-1 lesson as I will work with you personally to find the best option for your budget an needs, rather than just give a generic answer. \n        \n      \n\n      \n        \n      \n\n    \n  \n    \n\n      \n        \n      \n\n      \n        \n          \n            [about-icon] Why Take Beginners Photography Classes?\n          \n          \n            \n              \n                \n                \n              \n            \n          \n        \n      \n      \n        \n          Photography is more than just pointing and shooting; it's an art that demands technical proficiency and a sharp eye for composition. While you can grasp the photography basics through trial and error, signing up for a photography course for beginners will expedite your learning journey and help you sidestep common pitfalls. Here are some reasons why taking photography lessons is advantageous:Master Camera Settings: Understand the ins and outs of your camera, from automatic modes to manual exposure settings. Gain control over aperture, ISO, and shutter speed to achieve the desired effects in your images.Develop Composition Skills: Learn the principles of composition and how to create visually appealing photographs. Discover how to frame your subjects, balance elements, and use lighting to enhance your images.Expand Your Knowledge: Dive deeper into essential concepts such as exposure, focus, depth of field, and white balance. Understand the technical aspects of photography to unleash your creative potential.Receive Expert Guidance: Benefit from the expertise of a professional tutor who will guide you through the course. Alan Ranger, with his years of experience and passion for photography, will provide valuable insights and feedback to help you improve your skills.Structured Learning: Our beginners photography course is designed to provide a systematic and comprehensive learning experience. Each week, you'll focus on a specific aspect of photography, building upon your knowledge and skills.\n        \n      \n\n      \n        \n      \n\n    \n  \n    \n\n      \n        \n      \n\n      \n        \n          \n            [courses-icon] Summary\n          \n          \n            \n              \n                \n                \n              \n            \n          \n        \n      \n      \n        \n          This beginners photography classes will provide you with all the essential foundations on camera settings, composition and use of your equipment. With theory and practical lessons, together with assignments, you will be a more confident and knowledgeable photographer.Spaces for each course are limited, so make sure to secure your spot early. If you need to change your course date, please notify us at least four weeks in advance. Please note that a rebooking fee may apply for changes made within four weeks of the event date.Additional Opportunities for GrowthOnce you've completed our beginner's photography course, you may be interested in further honing your skills. We offer a range of intermediate masterclasses and courses to help you continue your photography journey:Editing Course with Lightroom for BeginnersRPS Course - Distinction MentoringThese next-step photography courses provide more advanced techniques, in-depth knowledge, and personalised mentoring to help you reach new heights in your photography.\n        \n      \n\n      \n        \n      \n\n    \n  \n\n\n              \n            \n          \n\n        \n      \n\n      \n\n  \n\n    \n\n\n\n\n\n\n\n\n\n\n\n\n\n\n\n\n\n\n\n\n  \n  \n\n\n\n\n\n  \n    \n      Get Access to Free Online Course\n      Sign up with your email address to access the Academy 101 Foundation Photography Course\n    \n    \n      \n        \n          \n            \n          \n            \n              \n              \n              \n                \n                  \n                \n                  First Name\n                  \n                \n              \n                  \n                \n                  Last Name\n                  \n                \n              \n                \n              \n            \n          \n        \n        \n          \n            \n              Email Address\n              \n            \n          \n        \n          \n        \n      \n      \n        \n          \n          Join today\n          \n        \n      \n      \n        \n      \n    \n    We respect your privacy.\n    Thank you! You will receive an email to verify and confirm your subscription to receive updates.  Please ensure you click the confirm button in the email.\n    \n  \n\n\n\n    \n      \n\n        \n          \n            \n              \n                Alan Ranger Photography\n                45 Hathaway Road,\n                Coventry, England, CV4 9HW,\n                United Kingdom\n              \n            \n            \n              +44 781 701 7994\n              info@alanranger.com\n            \n          \n        \n\n        \n          \n            \n              Hours\n              Mon 9am - 5pm\n              Tue 9am - 5pm\n              Wed 9am - 5pm\n              Thu 9am - 5pm\n              Fri 9am - 5pm\n              Sat 9am - 5pm\n              Sun 9am - 5pm\n            \n          \n        \n\n      \n\n      \n\n      \n  \n\n    Contact UsHelp - Site MapFree Online Photography CourseOnline - Zoom LessonsPrivate LessonsPhoto WorkshopsGift VouchersPhotography TipsSchedule an appointment\n\n  \n\n    \n\n    \n\n\n  Proud to be a member of\n\n\n\n\n\n\n\n\n\n\n\n\n\n\n\n\n\n\n\n\n\n  \n  \n\n\n\n\n\n\n\n\n\n\n\n\n\n\n\n\n\n\n\n\n\n\n\n\n\n\n\n\n\n\n\n\n\n\n\n\n\n\n\n\n\n\n\n\n\n\n  \n\n    \n  \n    \n\n      \n\n      \n        \n          \n        \n        \n\n        \n          \n            \n          \n            \n                \n                \n                \n                \n                \n                \n                \n                \n\n            \n          \n        \n          \n        \n\n        \n      \n        \n      \n\n    \n  \n\n\n  \n\n\n\n\n\n\n\n\n\n\n\n\n\n\n\n\n\n\n\n\n\n\n\n\n\n\n\n\n\n\n\n\n\n\n\n\n\n\n\n\n\n\n\n\n\n  \n\n    \n  \n    \n\n      \n\n      \n        \n          \n        \n        \n\n        \n          \n            \n          \n            \n                \n                \n                \n                \n                \n                \n                \n                \n\n            \n          \n        \n          \n        \n\n        \n      \n        \n      \n\n    \n  \n\n\n  \n\n\n\n\n\n\n\n\n\n\n\n\n\n\n\n\n\n\n\n\n\n\n\n\n\n\n\n\n\n\n\n\n\n\n\n\n\n\n\n\n\n\n\n\n\n  \n\n    \n  \n    \n\n      \n\n      \n        \n          \n        \n        \n\n        \n          \n            \n          \n            \n                \n                \n                \n                \n                \n                \n                \n                \n\n            \n          \n        \n          \n        \n\n        \n      \n        \n      \n\n    \n  \n\n\n  \n\n\n\n\n\n  Copyright Â© 2008-2025 Â Alan Ranger All Rights Reserved.  The Legal Stuff\n\n\n\n\n\n\n\n\n\n\n\n\n\n\n\n\n\n\n\n\n\n  \n  \n\n\n\n\n\n\n\n\n  \n    #block-yui_3_17_2_1_1651564402332_6670 .social-icons-style-border .sqs-svg-icon--wrapper {\n      \n        box-shadow: 0 0 0 2px inset;\n      \n      border: none; \n    }\n  \n  \n    \n      \n        \n          \n          \n        \n      \n    \n      \n        \n          \n          \n        \n      \n    \n      \n        \n          \n          \n        \n      \n    \n      \n        \n          \n          \n        \n      \n    \n      \n        \n          \n          \n        \n      \n    \n  \n\n\n\n\n  (44) 781-7017994 | info@alanranger.com45 Hathaway Road, Coventry, West Midlands, CV4 9HW, United Kingdom\n\n\n\n\n\n\n\n\n\n\n\n\n\n\n\n\n\n\n\n\n\n  \n  \n\n\n\n\n\n  \n\n\n\n\n    \n\n    \n    \n\n    \n\n\n\n\n\n\n\n{\n  \"@context\": \"http://schema.org\",\n  \"@type\": \"Organization\",\n  \"url\": \"https://www.alanranger.com/\",\n  \"logo\": \"https://www.alanranger.com/photography-tuition-icons/6ku1oah790lqdsn401bkwetsaai29o\",\n  \"contactPoint\": [{\n    \"@type\": \"ContactPoint\",\n    \"telephone\": \"+44-781-701-7994\",\n    \"contactType\": \"customer service\"\n  }]\n}\n\n\n\n\n\n(function () {\n  const removeProductSchema = () => {\n    const scripts = document.querySelectorAll('script[type=\"application/ld+json\"]');\n\n    scripts.forEach((script) => {\n      try {\n        const json = JSON.parse(script.textContent);\n\n        if (\n          json['@type'] === 'Product' ||\n          (Array.isArray(json['@type']) && json['@type'].includes('Product'))\n        ) {\n          // Optional safety: only remove if there's no review/aggregateRating\n          const hasReviewData = json.review || json.aggregateRating;\n          if (!hasReviewData) {\n            script.remove();\n          }\n        }\n      } catch (e) {\n        // Ignore malformed scripts\n      }\n    });\n  };\n\n  // Run once on DOM ready\n  document.addEventListener(\"DOMContentLoaded\", removeProductSchema);\n\n  // Run continuously for any future injections\n  const observer = new MutationObserver(() => {\n    removeProductSchema();\n  });\n\n  observer.observe(document.body, {\n    childList: true,\n    subtree: true\n  });\n})();\n\n\n\n\n\n\n\n\n\n\n\n!function(){window.self===window.top||window.top.document.getElementById(\"lazy-summaries-admin\")||function(e,t,s,i,a){if(s.querySelector(\"#\"+t))i&&i(this);else{var n=document.createElement(\"script\");n.src=e+\"?cache=\"+((new Date).getTime()+\"\").substr(0,8),n.id=t,n.onload=function(){a&&this.remove(),i&&i(this)},s.appendChild(n)}}(\"https://assets.squarewebsites.org/lazy-summaries/lazy-summaries-admin.js\",\"lazy-summaries-admin\",window.top.document.getElementsByTagName(\"head\")[0])}();\n\n\n\n\n\n\n window.customRegisterInterestSettings = {\n        '.collection-type-events.view-item': {\n            render: '.eventitem-column-meta',\n            source: '/register-interest',\n            text: 'Register interest',\n            alignment: 'left',\n            size: 'small'\n        },\n   \t\t'.collection-type-products.view-item': {\n            render: '.ProductItem-summary .sqs-add-to-cart-button-wrapper|after',\n            source: '/register-interest-product',\n            text: 'Register interest',\n            alignment: 'left', \n            size: 'small'\n        },\n}\n\n\n\n\n\n\n!(function() {\n    function injectScript(file, id, node) {\n        if (node.querySelector('#' + id)) {\n            return;\n        };\n        var script = document.createElement(\"script\");\n        script.src = file + '?cache=' + (new Date().getTime() + '').substr(0, 13);\n        script.id = id;\n        node.appendChild(script);\n    }\n    if (window.self !== window.top) {\n        document.addEventListener('DOMContentLoaded', function() {\n            setTimeout(function() {\n                injectScript('https://assets.squarewebsites.org/utils/csv-sync/alan-ranger/csv-sync.min.js?time='+(new Date).getTime(), 'csv-collection-sync', window.top.document.getElementsByTagName(\"head\")[0]);\n            }, 200)\n        })\n    }\n})();\n\n\n\ndocument.addEventListener('DOMContentLoaded', function(){\n\tsetTimeout(function(){window.self!==window.top&&(window.top.document.getElementById(\"sqs-admin-hooks\")||window.top.Y.Get.js(\"https://assets.squarewebsites.org/utils/sqs-admin-hooks/sqs-admin-hooks.js?time=\"+(new Date).getTime(),function(e,o){e?console.log(\"Error loading Admin Hooks Script: \"+e[0].error,\"error\"):(console.log(\"Admin Hooks Init\"),o&&o.nodes[0].setAttribute(\"id\",\"sqs-admin-hooks\"))}),window.top.document.getElementById(\"sqs-admin-hooks-date-to-events\")||window.top.Y.Get.js(\"https://assets.squarewebsites.org/utils/sqs-admin-hooks/prepend-date-to-events-descr-hook/date-to-events-descr-hook.js?time=\"+(new Date).getTime(),function(e,o){e?console.log(\"Error loading Admin Hooks Script: \"+e[0].error,\"error\"):(console.log(\"Add date if same description Init\"),o&&o.nodes[0].setAttribute(\"id\",\"sqs-admin-hooks-date-to-events\"))}),window.top.document.getElementById(\"events-collection-sync\")||window.top.Y.Get.js(\"https://assets.squarewebsites.org/utils/events-ical/alanranger-com.min.js?time=\"+(new Date).getTime(),function(e,o){e?console.log(\"Error loading Admin Hooks Script: \"+e[0].error,\"error\"):(console.log(\"Sync Calendar Events\"),o&&o.nodes[0].setAttribute(\"id\",\"events-collection-sync\"))}))}, 200)  \n});\n\n\n\n\n\n\nwindow.collectionsSyncConfig = {\n  \t gallery: {\n            enabled: true,\n            onlyDefined: false,\n       \t\tmoreThan: 1,\n            general : {\n                saveBody: false,\n                saveExcerpt: false,\n                useLZS: false\n            }\n    },\n    events: {\n            enabled: false,\n            onlyDefined: false,\n            general : {\n                saveBody: false,\n                saveExcerpt: false,\n                useLZS: false\n            }\n      },\n      blog: {\n            enabled: false,\n            onlyDefined: false,\n            general : {\n                saveBody: false,\n                saveExcerpt: true,\n                useLZS: true\n            }\n        },\n  \t  products: {\n            enabled: false,\n            onlyDefined: false,\n            general : {\n                saveBody: false,\n                saveExcerpt: true,\n                useLZS: true\n            }\n        }\n  };\n  \n!function(){if(window.self!==window.top){var n,e,o,t,i,c;window.top.document.getElementById(\"collections-index-sync\")||(window.collectionsSyncConfig&&(window.top.collectionsSyncConfig=window.collectionsSyncConfig),n=\"https://assets.squarewebsites.org/utils/collections-indexes/collections-sync.min.js\",e=window.top.document.getElementsByTagName(\"head\")[0],o=\"collections-index-sync\",(c=document.createElement(\"script\")).id=o,c.src=n+\"?cache=\"+((new Date).getTime()+\"\").substr(0,7),c.async=!0,c.onload=function(){i&&this.remove(),t&&t(null,{nodes:[this]})},e.appendChild(c))}}();\n\n\n\n//Filter\nvar monthNames = [\"January\", \"February\", \"March\", \"April\", \"May\", \"June\", \"July\", \"August\", \"September\", \"October\", \"November\", \"December\"];\nvar locations = [\"batsford\",\"coventry\",\"cumbria\",\"devon\",\"dorset\",\"glencoe\",\"hope-valley\",\"kenilworth\",\"lake- district\",\"norfolk\",\"northumbria\",\"solihull\",\"somerset\",\"suffolk\",\"warwickshire\",\"worcestershire\",\"yorkshire\",\"wales\",\"residential\",\"ireland\"];\n\n\n.custom-filter-container.custom-filter-view-dropdowns .customFiltersWrapper .sqs-block {\n  max-width: 33.33%\n  }\n\nwindow.customFilterSettings = {\n    'targets': [{\n            container: '.sqs-events-collection-list, #block-yui_3_17_2_1_1521549855177_44542,#block-yui_3_17_2_1_1564902899455_5204,#collection-53d39321e4b009befdb652c8 .ProductList,#collection-5eb7c3a098232c36f5d347d5 .ProductList',\n            items: '.eventlist-event--upcoming, .summary-item, .ProductList-item',\n            settings: {\n                placeFiltersTo: '.placeFilters',\n                position: 'top',\n                showItemsCount: true,\n                customClasses: '',\n                align: 'center',\n                useHistory: true,\n                updateFilterOptions: {\n                    enabled: true,\n                    nonExistOptions: {\n                        hide: false,\n                        disable: false,\n                        disableHard: false\n                    },\n                    showOptionsCounters: true,\n                    optionsCounterWrap: '- ()',\n                },\n                //keepDropdownsOpen: true,\n                simpleFilter: {\n                    show: {\n                        effect: 'fade',\n                        transitionDuration: 300,\n                        stagger: 30\n                    },\n                    hide: {\n                        effect: 'fade',\n                        transitionDuration: 100,\n                        stagger: 18\n                    }\n                },\n                hooks: {\n                    beforeCreate: function(target) {\n                        if (location.pathname.indexOf('/photography-shop') > -1 || location.pathname.indexOf('/photography-services') > -1) {\n                            target.settings.filter = {\n                                category: false,\n                                tag: false,\n                                items: [{\n                                        name: 'Categories',\n                                        multiple: true,\n                                        getAttr: 'categories'\n                                    },\n                                    {\n                                        name: 'Tag',\n                                        multiple: true,\n                                        notAllowedOptions: locations,\n                                        getAttr: 'tags'\n                                    },\n                                    {\n                                        name: 'Location',\n                                        multiple: false,\n                                        allowedOptions: locations,\n                                        getAttr: 'tags'\n                                    },\n                                ]\n                            }\n                        }\n                        if (location.pathname.indexOf('workshops') > -1) {\n                            target.settings.filter = {\n                                category: false,\n                                tag: false,\n                                items: [{\n                                        name: 'Workshops Location',\n                                        multiple: false,\n                                        getAttr: function(el, data) {\n                                            if (data && data.location && data.location.addressTitle) {\n                                                return data.location.addressTitle;\n                                            }\n                                            return false;\n                                        }\n                                    },\n                                    {\n                                        name: 'Workshops Duration',\n                                        multiple: true,\n                                        getAttr: 'categories'\n                                    }, {\n                                        name: 'Workshops Year',\n                                        multiple: false,\n                                        getAttr: function(it, data) {\n                                            it = it._node || it;\n                                            var time = it.querySelector('[datetime]');\n                                            if (time) {\n                                                time = time.getAttribute('datetime').substr(0, 4);\n                                                return time;\n                                            } else if (data && data.startDate) {\n                                                return new Date(data.startDate).getFullYear()\n                                            }\n                                        }\n                                    },\n                                    {\n                                        name: 'Workshops Month',\n                                        multiple: false,\n                                        allowedOptions: monthNames,\n                                        sort: 'asAllowed',\n                                        getAttr: function(it, data) {\n                                            it = it._node || it;\n                                            var time = it.querySelector('[datetime]');\n                                            if (time) {\n                                                time = new Date(time.getAttribute('datetime')).toLocaleString('default', { month: 'long' });\n                                                return time;\n                                            } else if (data && data.startDate) {\n                                                return new Date(data.startDate).toLocaleString('default', { month: 'long' });\n                                            }\n                                        }\n                                    },\n                                    {\n                                        name: 'Tag',\n                                        multiple: true,\n                                        getAttr: 'tags'\n                                    }\n                                ]\n                            }\n                        }\n                        if (location.pathname.indexOf('course') > -1 || location.pathname.indexOf('classes') > -1) {\n                            target.settings.filter = {\n                                category: false,\n                                tag: false,\n                                items: [{\n                                        name: 'Courses Location',\n                                        multiple: true,\n                                        getAttr: function(el, data) {\n                                            if (data && data.location && data.location.addressTitle) {\n                                                return data.location.addressTitle;\n                                            }\n                                            return false;\n                                        }\n                                    },\n                                    {\n                                        name: 'Courses Categories',\n                                        multiple: true,\n                                        getAttr: 'categories'\n                                    }, {\n                                        name: 'Courses Year',\n                                        multiple: false,\n                                        getAttr: function(it, data) {\n                                            it = it._node || it;\n                                            var time = it.querySelector('[datetime]');\n                                            if (time) {\n                                                time = time.getAttribute('datetime').substr(0, 4);\n                                                return time;\n                                            } else if (data && data.startDate) {\n                                                return new Date(data.startDate).getFullYear()\n                                            }\n                                        }\n                                    }, {\n                                        name: 'Courses Month',\n                                        multiple: false,\n                                        allowedOptions: monthNames,\n                                        sort: 'asAllowed',\n                                        getAttr: function(it, data) {\n                                            it = it._node || it;\n                                            var time = it.querySelector('[datetime]');\n                                            if (time) {\n                                                time = new Date(time.getAttribute('datetime')).toLocaleString('default', { month: 'long' });\n                                                return time;\n                                            } else if (data && data.startDate) {\n                                                return new Date(data.startDate).toLocaleString('default', { month: 'long' });\n                                            }\n                                        }\n                                    }, {\n                                        name: 'Tag',\n                                        multiple: true,\n                                        getAttr: 'tags'\n                                    }\n                                ]\n                            }\n                        }\n                        if (location.pathname.indexOf('/photographic-workshops') > -1) {\n                            target.settings.position = 'top';\n                            //target.settings.customIndexUrl = '/workshops-events-custom-index';\n                        } else if (location.pathname.indexOf('/photography-classes') > -1) {\n                            target.settings.position = 'top';\n                            //target.settings.customIndexUrl = '/classes-events-custom-index';\n                        }\n                    }\n                },\n                sort: {\n                    items: [{\n                            name: 'A-Z',\n                            order: 'asc',\n                            sort: function(el, data) {\n                                if (data) {\n                                    return data.title;\n                                }\n                            }\n                        },\n                        {\n                            name: 'Z-A',\n                            order: 'desc',\n                            sort: function(el, data) {\n                                if (data) {\n                                    return data.title;\n                                }\n                            }\n                        },\n                        {\n                            name: 'Date',\n                            order: 'asc|desc',\n                            sort: function(el, data) {\n                                var result = 1;\n                                if (data && data.id) {\n                                    result = data.startDate;\n                                }\n                                return result;\n                            }\n                        }\n                    ]\n                }\n            }\n        },\n        {\n            container: '#collection-53836c32e4b05b1c55576880 .BlogList, #block-yui_3_17_2_1_1529137402624_4143',\n            items: '.hentry, .summary-item',\n            settings: {\n                //placeFiltersTo: '.collection-header',\n                position: 'top',\n                useSessionCache: false,\n                showItemsCount: true,\n                useHistory: true,\n                //keepDropdownsOpen: true,\n                updateFilterOptions: {\n                    enabled: true,\n                    nonExistOptions: {\n                        hide: false,\n                        disable: false,\n                        disableHard: false\n                    },\n                    showOptionsCounters: true,\n                    optionsCounterWrap: '- ()',\n                },\n                hooks: {\n                    beforeCreate: function(target) {\n                        if (window.top && window.top.Static && window.top.Static.IN_BACKEND) {\n                            target.noNeedCreate = true;\n                        }\n                    },\n                    beforeInit: function(filter) {\n                        //console.log(filter.target.settings)\n                        if (Y.one('body').hasClass('view-list')) {\n                            //filter.target.settings.customIndexUrl = '/blog-blog-custom-index';\n                        }\n                    },\n                    onInit: function(filter) {\n                        filter.target.settings.pagination.loadMoreButton.enabled = false;\n                    }\n                },\n                simpleFilter: {\n                    show: {\n                        effect: 'fade',\n                        transitionDuration: 300,\n                        stagger: 30\n                    },\n                    hide: {\n                        effect: 'fade',\n                        transitionDuration: 100,\n                        stagger: 18\n                    }\n                },\n                sort: {\n                    items: [{\n                        name: 'A-Z',\n                        order: 'asc',\n                        sort: function(el, data) {\n                            var title = '';\n                            if (data) {\n                                title = data.title;\n                            }\n                            return title;\n                        }\n                    }, {\n                        name: 'Z-A',\n                        order: 'desc',\n                        sort: function(el, data) {\n                            var title = '';\n                            if (data) {\n                                title = data.title;\n                            }\n                            return title;\n                        }\n                    }, {\n                        name: 'Date',\n                        order: 'asc|desc',\n                        sort: function(el, data) {\n                            var result = 1;\n                            if (data && data.id) {\n                                result = data.publishOn;\n                            }\n                            return result;\n                        }\n                    }]\n                },\n                pagination: {\n                    enabled: true,\n                    pageSize: 8,\n                    place: \"bottom\",\n                    showPrevNext: { //will show next/prev elements arrows\n                        enabled: true,\n                        //hideItems: true,\n                        next: 'Next', //next link text\n                        prev: 'Prev' //previous link text\n                    },\n                    loadMoreButton: {\n                        enabled: false\n                    }\n                },\n                filter: {\n                    category: false,\n                    tag: false,\n                    items: [{\n                        name: 'Category',\n                        multiple: true,\n                        getAttr: 'categories'\n                    }, {\n                        name: 'Tag',\n                        multiple: true,\n                        getAttr: 'tags'\n                    }]\n                }\n            }\n        }\n    ]\n};\n\n\n\n\n\n\n\n!function(){window.self===window.top||window.document.getElementById(\"sqstp-UI-theme-script\")||function(e,t,s,i,a){if(s.querySelector(\"#\"+t))i&&i(this);else{var n=document.createElement(\"script\");n.src=e+\"?cache=\"+((new Date).getTime()+\"\").substr(0,8),n.async=!0,n.id=t,n.onload=function(){a&&this.remove(),i&&i(this)},s.appendChild(n)}}(\"https://plugins.squarewebsites.org/sqstools-ext/themes/modern.min.js\",\"sqstp-UI-theme-script\",window.document.getElementsByTagName(\"head\")[0])}();\n\n\n\n\n\n\n\n$( \".reading-time\" ).insertBefore( \"h1.BlogItem-title\" );\n\n\n\n\n\n  var scrolled = 400; $(window).scroll(function() {\n    if ( $(window).scrollTop() > scrolled ) {\n      $('a.btt').fadeIn('slow');\n    } else {\n      $('a.btt').fadeOut('slow');\n    }\n  });\n\n\n  $('a.btt').click(function() {\n    $('html, body').animate({ scrollTop: 0 }, 700);\n    return false;\n  });\n\n\n\n\n$(document).ready(function () {\n    // Define the hover timeout duration in milliseconds\n    var hoverTimeoutDuration = 3000; // Example: 3000ms (3 seconds)\n\n    $('.Header-nav-folder-title[href^=\"/mega-\"]').each(function () {\n        var e = $(this).attr(\"href\").slice(6);\n        $(this).parent().addClass(\"mega-menu\");\n        var a = $(this).closest(\"header.Header\");\n        a.append(\"<div id=\" + e + ' class=\"mega-menu-item\"></div>');\n        $(\"#\" + e).load(\"/mega-menu-pages #mega-page-\" + e, function () {\n            window.Squarespace.initializeLayoutBlocks(Y, Y.one(\"#\" + e));\n            var imgs = document.querySelectorAll(\".mega-menu-item img[data-src]\");\n            for (var n = 0; n < imgs.length; n++) {\n                ImageLoader.load(imgs[n], { load: true, fill: true });\n                imgs[n].parentNode.className += \" loaded\";\n            }\n        });\n        var hoverTimeout;\n        // Function to start hover timeout\n        function startHoverTimeout() {\n            clearTimeout(hoverTimeout);\n            hoverTimeout = setTimeout(function () {\n                removeHoverFromAll();\n            }, hoverTimeoutDuration);\n        }\n        // Function to remove hover from all mega menus\n        function removeHoverFromAll() {\n            $('.mega-menu-item').removeClass('hover');\n            $('.mega-menu').removeClass('hover');\n        }\n        // Handle hover on the link's parent\n        $(this).parent().hover(\n            function () {\n                removeHoverFromAll(); // Remove hover from all other mega menus\n                a.find(\"#\" + e).addClass(\"hover\");\n                clearTimeout(hoverTimeout);\n                // Monitor mouse movement to reset hover timeout\n                $(document).on(\"mousemove.megaMenu\", function () {\n                    clearTimeout(hoverTimeout);\n                    startHoverTimeout();\n                });\n            },\n            function () {\n                startHoverTimeout();\n                $(document).off(\"mousemove.megaMenu\");\n            }\n        );\n        // Handle hover on the mega menu content\n        $(\"#\" + e).hover(\n            function () {\n                a.find(\"#\" + e).addClass(\"hover\");\n                clearTimeout(hoverTimeout);\n\n                // Monitor mouse movement to reset hover timeout\n                $(document).on(\"mousemove.megaMenuContent\", function () {\n                    clearTimeout(hoverTimeout);\n                    startHoverTimeout();\n                });\n            },\n            function () {\n                startHoverTimeout();\n                $(document).off(\"mousemove.megaMenuContent\");\n            }\n        );\n        // Detect hover on anything outside the mega menu or its link\n        $(\"body\").on(\"mouseenter\", \"","fitness_level":null,"what_to_bring":null,"course_duration":"in milliseconds","instructor_info":null,"availability_status":null,"meta_description":"The three-week beginners photography classes will teach you the fundamentals of camera operation and composition. Enrol today and start improving your images.","csv_metadata":{"kind":"service","title":null}},{"id":244504,"url":"https://www.alanranger.com/course-finder-photography-classes-near-me","kind":"service","title":"Best Photography Classes Near Me - Course Finder - Coventry","description":"UK Landscape Photography Workshops, Beginners Courses and Private Lessons - Enhance your skill with Alan Ranger Photography - Qualified Tutor and Professional Photographer","date_start":null,"date_end":null,"location":null,"price":null,"price_currency":null,"availability":null,"sku":null,"provider":"Alan Ranger Photography","source_url":"https://www.alanranger.com/course-finder-photography-classes-near-me","raw":{"url":"https://www.alanranger.com","name":"Alan Ranger Photography","@type":"WebSite","image":"//images.squarespace-cdn.com/content/v1/5013f4b2c4aaa4752ac69b17/b859ad2b-1442-4595-b9a4-410c32299bf8/ALAN+RANGER+photography+LOGO+BLACK.+switched+small.png","@context":"http://schema.org","description":"<p class=\"\" style=\"white-space:pre-wrap;\">UK Landscape Photography Workshops,&nbsp;Beginners Courses and Private Lessons - Enhance your skill with Alan Ranger Photography - Qualified Tutor and Professional Photographer</p>"},"entity_hash":"292ec870b9b7cf21f33eb4bfec48fb7975d6ae99","last_seen":"2025-10-29T17:53:24.133+00:00","page_url":"https://www.alanranger.com/course-finder-photography-classes-near-me","norm_title":"best photography classes near me - course finder - coventry","start_date":null,"csv_type":"landing_service_pages","csv_metadata_id":70594,"categories":null,"tags":null,"publish_date":null,"location_name":null,"location_address":"s","excerpt":null,"end_date":null,"start_time":null,"end_time":null,"location_city_state_zip":null,"image_url":null,"json_ld_data":null,"workflow_state":null,"participants":null,"experience_level":null,"equipment_needed":null,"time_schedule":"-15-10","fitness_level":null,"what_to_bring":null,"course_duration":"in milliseconds","instructor_info":null,"availability_status":null,"meta_description":"Learn and master the art of photography with the best photography classes near me!  Course Finder for photography lessons in Coventry or Online - To Suit You","csv_metadata":{"kind":"service","title":null}},{"id":244520,"url":"https://www.alanranger.com/photography-courses-coventry","kind":"service","title":"Top Photography Courses Coventry - Or Online With a Pro","description":"UK Landscape Photography Workshops, Beginners Courses and Private Lessons - Enhance your skill with Alan Ranger Photography - Qualified Tutor and Professional Photographer","date_start":null,"date_end":null,"location":null,"price":null,"price_currency":null,"availability":null,"sku":null,"provider":"Alan Ranger Photography","source_url":"https://www.alanranger.com/photography-courses-coventry","raw":{"url":"https://www.alanranger.com","name":"Alan Ranger Photography","@type":"WebSite","image":"//images.squarespace-cdn.com/content/v1/5013f4b2c4aaa4752ac69b17/b859ad2b-1442-4595-b9a4-410c32299bf8/ALAN+RANGER+photography+LOGO+BLACK.+switched+small.png","@context":"http://schema.org","description":"<p class=\"\" style=\"white-space:pre-wrap;\">UK Landscape Photography Workshops,&nbsp;Beginners Courses and Private Lessons - Enhance your skill with Alan Ranger Photography - Qualified Tutor and Professional Photographer</p>"},"entity_hash":"81de06fe929043cdb8c69fc7542ce355a24599bd","last_seen":"2025-10-29T17:53:23.611+00:00","page_url":"https://www.alanranger.com/photography-courses-coventry","norm_title":"top photography courses coventry - or online with a pro","start_date":null,"csv_type":"landing_service_pages","csv_metadata_id":70593,"categories":null,"tags":null,"publish_date":null,"location_name":null,"location_address":"with a photography workshop.","excerpt":null,"end_date":null,"start_time":null,"end_time":null,"location_city_state_zip":null,"image_url":null,"json_ld_data":null,"workflow_state":null,"participants":null,"experience_level":null,"equipment_needed":null,"time_schedule":"out duration in milliseconds","fitness_level":null,"what_to_bring":null,"course_duration":"in milliseconds","instructor_info":null,"availability_status":null,"meta_description":"Beginner photography courses Coventry or online â?? to suit any level of experience, camera, or budget. Learn photography basics with a professional tutor.","csv_metadata":{"kind":"service","title":null}},{"id":244633,"url":"https://www.alanranger.com/photo-workshops-uk","kind":"service","title":"Photo Workshops UK | Landscape Photography Workshops","description":"PHOTO WORKSHOPS UK | LANDSCAPE PHOTOGRAPHY WORKSHOPS","date_start":null,"date_end":null,"location":null,"price":null,"price_currency":null,"availability":null,"sku":null,"provider":"Alan Ranger Photography","source_url":"https://www.alanranger.com/photo-workshops-uk","raw":{"name":"Alan Ranger Photography","@type":"LocalBusiness","image":"https://static1.squarespace.com/static/5013f4b2c4aaa4752ac69b17/t/6749dba3f5275a74ca88a3bd/1761580471344/","address":"45 Hathaway Road\nCoventry, England, CV4 9HW\nUnited Kingdom","@context":"http://schema.org","openingHours":"Mo 09:00-17:00, Tu 09:00-17:00, We 09:00-17:00, Th 09:00-17:00, Fr 09:00-17:00, Sa 09:00-17:00, Su 09:00-17:00"},"entity_hash":"15a0021851db0fa0832d283957b9b267f6cffadd","last_seen":"2025-10-29T17:53:13.321+00:00","page_url":"https://www.alanranger.com/photo-workshops-uk","norm_title":"photo workshops uk | landscape photography workshops","start_date":null,"csv_type":"landing_service_pages","csv_metadata_id":70631,"categories":null,"tags":null,"publish_date":null,"location_name":null,"location_address":".pathname.indexOf('/photography-services') > -1) {","excerpt":null,"end_date":null,"start_time":null,"end_time":null,"location_city_state_zip":null,"image_url":null,"json_ld_data":null,"workflow_state":null,"participants":null,"experience_level":null,"equipment_needed":null,"time_schedule":"out duration in milliseconds","fitness_level":null,"what_to_bring":null,"course_duration":"in milliseconds","instructor_info":null,"availability_status":null,"meta_description":"Join our immersive landscape photo workshops in the UK to refine your skills and capture stunning natural beauty. Learn from expert professional photographers.","csv_metadata":{"kind":"service","title":null}}]},"structured":{"intent":"services","topic":"types, photography, services, offer","services":[{"id":257590,"url":"https://www.alanranger.com/photographic-workshops-near-me","kind":"event","title":"Photographic Workshops Near Me","description":"LANDSCAPE PHOTOGRAPHIC WORKSHOPS NEAR ME 2025 - 2026","date_start":null,"date_end":null,"location":null,"price":null,"price_currency":null,"availability":null,"sku":null,"provider":"Alan Ranger Photography","source_url":"https://www.alanranger.com/photographic-workshops-near-me","raw":{"name":"Alan Ranger Photography","@type":"LocalBusiness","image":"https://static1.squarespace.com/static/5013f4b2c4aaa4752ac69b17/t/6749dba3f5275a74ca88a3bd/1761580471344/","address":"45 Hathaway Road\nCoventry, England, CV4 9HW\nUnited Kingdom","@context":"http://schema.org","openingHours":"Mo 09:00-17:00, Tu 09:00-17:00, We 09:00-17:00, Th 09:00-17:00, Fr 09:00-17:00, Sa 09:00-17:00, Su 09:00-17:00","_csv_end_time":null,"_csv_start_time":null},"entity_hash":"af02d9f62092b020bd2e8ca561861798ca70a33c","last_seen":"2025-10-29T18:30:50.426+00:00","page_url":"https://www.alanranger.com/photographic-workshops-near-me","norm_title":"alan ranger photography","start_date":null,"csv_type":"landing_service_pages","csv_metadata_id":70629,"categories":null,"tags":null,"publish_date":null,"location_name":null,"location_address":null,"excerpt":null,"end_date":null,"start_time":null,"end_time":null,"location_city_state_zip":null,"image_url":null,"json_ld_data":null,"workflow_state":null,"participants":null,"experience_level":null,"equipment_needed":null,"time_schedule":null,"fitness_level":null,"what_to_bring":null,"course_duration":"in milliseconds","instructor_info":null,"availability_status":null,"meta_description":null,"csv_metadata":{"kind":"service","title":null}},{"id":257688,"url":"https://www.alanranger.com/photography-services-near-me/camera-sensor-clean","kind":"service","title":"Professional Digital DSLR Camera Sensor Clean | Coventry","description":"UK Landscape Photography Workshops, Beginners Courses and Private Lessons - Enhance your skill with Alan Ranger Photography - Qualified Tutor and Professional Photographer","date_start":null,"date_end":null,"location":null,"price":null,"price_currency":null,"availability":null,"sku":null,"provider":"Alan Ranger Photography","source_url":"https://www.alanranger.com/photography-services-near-me/camera-sensor-clean","raw":{"url":"https://www.alanranger.com","name":"Alan Ranger Photography","@type":"WebSite","image":"//images.squarespace-cdn.com/content/v1/5013f4b2c4aaa4752ac69b17/b859ad2b-1442-4595-b9a4-410c32299bf8/ALAN+RANGER+photography+LOGO+BLACK.+switched+small.png","@context":"http://schema.org","description":"<p class=\"\" style=\"white-space:pre-wrap;\">UK Landscape Photography Workshops,&nbsp;Beginners Courses and Private Lessons - Enhance your skill with Alan Ranger Photography - Qualified Tutor and Professional Photographer</p>"},"entity_hash":"12456203015a25e561b5aa5d0ece9e33390a8b4b","last_seen":"2025-10-29T18:30:48.63+00:00","page_url":"https://www.alanranger.com/photography-services-near-me/camera-sensor-clean","norm_title":"professional digital dslr camera sensor clean | coventry","start_date":null,"csv_type":"landing_service_pages","csv_metadata_id":70746,"categories":["photography-services"],"tags":["sensor clean"],"publish_date":"2014-07-26","location_name":null,"location_address":"Drop and collect - 45 Hathaway Road, Coventry, CV4 9HWDuration: 60 mins, but the camera is to be collected the following day unless expressly agreed soonerPlease bring a camera with an empty memory card and lens attachedFully charged battery (Important otherwise, I may not be able to clean the sensor)\n\n\n\n\n\n\n\n\n\n\n\n\n\n\n\n\n\n\n\n\n\n  \n  \n\n\n\n\t\t\t\t\t\t\t\t\t\t\t\t\t\t\t\t\t\t\t\t\t\t\t\t\t\t\t\t\t\t\t\t\t\n\t\t\t\n{\n  \"@context\": \"https://schema.org/\",\n  \"@type\": \"Product\",\n  \"name\": \"Professional Digital DSLR Camera Sensor Clean | Coventry\",\n  \"image\": \"https://images.squarespace-cdn.com/content/v1/5013f4b2c4aaa4752ac69b17/1522495201980-KD6BKH54J01HJR93XXR6/photography-support-Services-1.png https://images.squarespace-cdn.com/content/v1/5013f4b2c4aaa4752ac69b17/1706983612066-FCM4V2DFPEUGVDMQNA7I/Camera+Sensor+Clean.jpg\",\n  \"description\": \"style=\\\"white-space:pre-wrap;\\\">Get a camera sensor clean in Coventry . Sensor checked and cleaned using professional equipment, swabs | Full Frame and Cropped Sensors | 24hr Turnaround\",\n  \"url\": \"https://www.alanranger.com/photography-services-near-me/camera-sensor-clean\",\n  \"offers\": {\n    \"@type\": \"Offer\",\n    \"priceCurrency\": \"GBP\",\n    \"price\": 30.0,\n    \"availability\": \"http://schema.org/InStock\",\n    \"shippingDetails\": {\n      \"@type\": \"OfferShippingDetails\",\n      \"doesNotShip\": \"http://schema.org/True\",\n      \"shippingDestination\": {\n        \"@type\": \"DefinedRegion\",\n        \"addressCountry\": \"GB\"\n      }\n    },\n    \"hasMerchantReturnPolicy\": {\n      \"@type\": \"MerchantReturnPolicy\",\n      \"returnPolicyCategory\": \"http://schema.org/MerchantReturnFiniteReturnWindow\",\n      \"merchantReturnDays\": 28,\n      \"returnMethod\": \"http://schema.org/ReturnByMail\",\n      \"returnFees\": \"http://schema.org/FreeReturn\",\n      \"applicableCountry\": \"GB\",\n      \"refundType\": \"http://schema.org/FullRefund\"\n    }\n  }\n}\n\n    \n    \n\n    \n\n      \n\n    \n\n    \n\n  \n\n\n\ndocument.querySelector('.ProductItem-details .sqs-add-to-cart-button').classList.remove('sqs-editable-button');\n              \n            \n          \n\n        \n      \n\n      \n\n  \n\n    \n\n\n\n\n\n\n\n\n\n\n\n\n\n\n\n\n\n\n\n\n  \n  \n\n\n\n\n\n  \n    \n      Get Access to Free Online Course\n      Sign up with your email address to access the Academy 101 Foundation Photography Course\n    \n    \n      \n        \n          \n            \n          \n            \n              \n              \n              \n                \n                  \n                \n                  First Name\n                  \n                \n              \n                  \n                \n                  Last Name\n                  \n                \n              \n                \n              \n            \n          \n        \n        \n          \n            \n              Email Address\n              \n            \n          \n        \n          \n        \n      \n      \n        \n          \n          Join today\n          \n        \n      \n      \n        \n      \n    \n    We respect your privacy.\n    Thank you! You will receive an email to verify and confirm your subscription to receive updates.  Please ensure you click the confirm button in the email.\n    \n  \n\n\n\n    \n      \n\n        \n          \n            \n              \n                Alan Ranger Photography\n                45 Hathaway Road,\n                Coventry, England, CV4 9HW,\n                United Kingdom\n              \n            \n            \n              +44 781 701 7994\n              info@alanranger.com\n            \n          \n        \n\n        \n          \n            \n              Hours\n              Mon 9am - 5pm\n              Tue 9am - 5pm\n              Wed 9am - 5pm\n              Thu 9am - 5pm\n              Fri 9am - 5pm\n              Sat 9am - 5pm\n              Sun 9am - 5pm\n            \n          \n        \n\n      \n\n      \n\n      \n  \n\n    Contact UsHelp - Site MapFree Online Photography CourseOnline - Zoom LessonsPrivate LessonsPhoto WorkshopsGift VouchersPhotography TipsSchedule an appointment\n\n  \n\n    \n\n    \n\n\n  Proud to be a member of\n\n\n\n\n\n\n\n\n\n\n\n\n\n\n\n\n\n\n\n\n\n  \n  \n\n\n\n\n\n\n\n\n\n\n\n\n\n\n\n\n\n\n\n\n\n\n\n\n\n\n\n\n\n\n\n\n\n\n\n\n\n\n\n\n\n\n\n\n\n\n  \n\n    \n  \n    \n\n      \n\n      \n        \n          \n        \n        \n\n        \n          \n            \n          \n            \n                \n                \n                \n                \n                \n                \n                \n                \n\n            \n          \n        \n          \n        \n\n        \n      \n        \n      \n\n    \n  \n\n\n  \n\n\n\n\n\n\n\n\n\n\n\n\n\n\n\n\n\n\n\n\n\n\n\n\n\n\n\n\n\n\n\n\n\n\n\n\n\n\n\n\n\n\n\n\n\n  \n\n    \n  \n    \n\n      \n\n      \n        \n          \n        \n        \n\n        \n          \n            \n          \n            \n                \n                \n                \n                \n                \n                \n                \n                \n\n            \n          \n        \n          \n        \n\n        \n      \n        \n      \n\n    \n  \n\n\n  \n\n\n\n\n\n\n\n\n\n\n\n\n\n\n\n\n\n\n\n\n\n\n\n\n\n\n\n\n\n\n\n\n\n\n\n\n\n\n\n\n\n\n\n\n\n  \n\n    \n  \n    \n\n      \n\n      \n        \n          \n        \n        \n\n        \n          \n            \n          \n            \n                \n                \n                \n                \n                \n                \n                \n                \n\n            \n          \n        \n          \n        \n\n        \n      \n        \n      \n\n    \n  \n\n\n  \n\n\n\n\n\n  Copyright Â© 2008-2025 Â Alan Ranger All Rights Reserved.  The Legal Stuff\n\n\n\n\n\n\n\n\n\n\n\n\n\n\n\n\n\n\n\n\n\n  \n  \n\n\n\n\n\n\n\n\n  \n    #block-yui_3_17_2_1_1651564402332_6670 .social-icons-style-border .sqs-svg-icon--wrapper {\n      \n        box-shadow: 0 0 0 2px inset;\n      \n      border: none; \n    }\n  \n  \n    \n      \n        \n          \n          \n        \n      \n    \n      \n        \n          \n          \n        \n      \n    \n      \n        \n          \n          \n        \n      \n    \n      \n        \n          \n          \n        \n      \n    \n      \n        \n          \n          \n        \n      \n    \n  \n\n\n\n\n  (44) 781-7017994 | info@alanranger.com45 Hathaway Road, Coventry, West Midlands, CV4 9HW, United Kingdom\n\n\n\n\n\n\n\n\n\n\n\n\n\n\n\n\n\n\n\n\n\n  \n  \n\n\n\n\n\n  \n\n\n\n\n    \n\n    \n    \n\n    \n\n\n\n\n\n\n\n{\n  \"@context\": \"http://schema.org\",\n  \"@type\": \"Organization\",\n  \"url\": \"https://www.alanranger.com/\",\n  \"logo\": \"https://www.alanranger.com/photography-tuition-icons/6ku1oah790lqdsn401bkwetsaai29o\",\n  \"contactPoint\": [{\n    \"@type\": \"ContactPoint\",\n    \"telephone\": \"+44-781-701-7994\",\n    \"contactType\": \"customer service\"\n  }]\n}\n\n\n\n\n\n(function () {\n  const removeProductSchema = () => {\n    const scripts = document.querySelectorAll('script[type=\"application/ld+json\"]');\n\n    scripts.forEach((script) => {\n      try {\n        const json = JSON.parse(script.textContent);\n\n        if (\n          json['@type'] === 'Product' ||\n          (Array.isArray(json['@type']) && json['@type'].includes('Product'))\n        ) {\n          // Optional safety: only remove if there's no review/aggregateRating\n          const hasReviewData = json.review || json.aggregateRating;\n          if (!hasReviewData) {\n            script.remove();\n          }\n        }\n      } catch (e) {\n        // Ignore malformed scripts\n      }\n    });\n  };\n\n  // Run once on DOM ready\n  document.addEventListener(\"DOMContentLoaded\", removeProductSchema);\n\n  // Run continuously for any future injections\n  const observer = new MutationObserver(() => {\n    removeProductSchema();\n  });\n\n  observer.observe(document.body, {\n    childList: true,\n    subtree: true\n  });\n})();\n\n\n\n\n\n\n\n\n\n\n\n!function(){window.self===window.top||window.top.document.getElementById(\"lazy-summaries-admin\")||function(e,t,s,i,a){if(s.querySelector(\"#\"+t))i&&i(this);else{var n=document.createElement(\"script\");n.src=e+\"?cache=\"+((new Date).getTime()+\"\").substr(0,8),n.id=t,n.onload=function(){a&&this.remove(),i&&i(this)},s.appendChild(n)}}(\"https://assets.squarewebsites.org/lazy-summaries/lazy-summaries-admin.js\",\"lazy-summaries-admin\",window.top.document.getElementsByTagName(\"head\")[0])}();\n\n\n\n\n\n\n window.customRegisterInterestSettings = {\n        '.collection-type-events.view-item': {\n            render: '.eventitem-column-meta',\n            source: '/register-interest',\n            text: 'Register interest',\n            alignment: 'left',\n            size: 'small'\n        },\n   \t\t'.collection-type-products.view-item': {\n            render: '.ProductItem-summary .sqs-add-to-cart-button-wrapper|after',\n            source: '/register-interest-product',\n            text: 'Register interest',\n            alignment: 'left', \n            size: 'small'\n        },\n}\n\n\n\n\n\n\n!(function() {\n    function injectScript(file, id, node) {\n        if (node.querySelector('#' + id)) {\n            return;\n        };\n        var script = document.createElement(\"script\");\n        script.src = file + '?cache=' + (new Date().getTime() + '').substr(0, 13);\n        script.id = id;\n        node.appendChild(script);\n    }\n    if (window.self !== window.top) {\n        document.addEventListener('DOMContentLoaded', function() {\n            setTimeout(function() {\n                injectScript('https://assets.squarewebsites.org/utils/csv-sync/alan-ranger/csv-sync.min.js?time='+(new Date).getTime(), 'csv-collection-sync', window.top.document.getElementsByTagName(\"head\")[0]);\n            }, 200)\n        })\n    }\n})();\n\n\n\ndocument.addEventListener('DOMContentLoaded', function(){\n\tsetTimeout(function(){window.self!==window.top&&(window.top.document.getElementById(\"sqs-admin-hooks\")||window.top.Y.Get.js(\"https://assets.squarewebsites.org/utils/sqs-admin-hooks/sqs-admin-hooks.js?time=\"+(new Date).getTime(),function(e,o){e?console.log(\"Error loading Admin Hooks Script: \"+e[0].error,\"error\"):(console.log(\"Admin Hooks Init\"),o&&o.nodes[0].setAttribute(\"id\",\"sqs-admin-hooks\"))}),window.top.document.getElementById(\"sqs-admin-hooks-date-to-events\")||window.top.Y.Get.js(\"https://assets.squarewebsites.org/utils/sqs-admin-hooks/prepend-date-to-events-descr-hook/date-to-events-descr-hook.js?time=\"+(new Date).getTime(),function(e,o){e?console.log(\"Error loading Admin Hooks Script: \"+e[0].error,\"error\"):(console.log(\"Add date if same description Init\"),o&&o.nodes[0].setAttribute(\"id\",\"sqs-admin-hooks-date-to-events\"))}),window.top.document.getElementById(\"events-collection-sync\")||window.top.Y.Get.js(\"https://assets.squarewebsites.org/utils/events-ical/alanranger-com.min.js?time=\"+(new Date).getTime(),function(e,o){e?console.log(\"Error loading Admin Hooks Script: \"+e[0].error,\"error\"):(console.log(\"Sync Calendar Events\"),o&&o.nodes[0].setAttribute(\"id\",\"events-collection-sync\"))}))}, 200)  \n});\n\n\n\n\n\n\nwindow.collectionsSyncConfig = {\n  \t gallery: {\n            enabled: true,\n            onlyDefined: false,\n       \t\tmoreThan: 1,\n            general : {\n                saveBody: false,\n                saveExcerpt: false,\n                useLZS: false\n            }\n    },\n    events: {\n            enabled: false,\n            onlyDefined: false,\n            general : {\n                saveBody: false,\n                saveExcerpt: false,\n                useLZS: false\n            }\n      },\n      blog: {\n            enabled: false,\n            onlyDefined: false,\n            general : {\n                saveBody: false,\n                saveExcerpt: true,\n                useLZS: true\n            }\n        },\n  \t  products: {\n            enabled: false,\n            onlyDefined: false,\n            general : {\n                saveBody: false,\n                saveExcerpt: true,\n                useLZS: true\n            }\n        }\n  };\n  \n!function(){if(window.self!==window.top){var n,e,o,t,i,c;window.top.document.getElementById(\"collections-index-sync\")||(window.collectionsSyncConfig&&(window.top.collectionsSyncConfig=window.collectionsSyncConfig),n=\"https://assets.squarewebsites.org/utils/collections-indexes/collections-sync.min.js\",e=window.top.document.getElementsByTagName(\"head\")[0],o=\"collections-index-sync\",(c=document.createElement(\"script\")).id=o,c.src=n+\"?cache=\"+((new Date).getTime()+\"\").substr(0,7),c.async=!0,c.onload=function(){i&&this.remove(),t&&t(null,{nodes:[this]})},e.appendChild(c))}}();\n\n\n\n//Filter\nvar monthNames = [\"January\", \"February\", \"March\", \"April\", \"May\", \"June\", \"July\", \"August\", \"September\", \"October\", \"November\", \"December\"];\nvar locations = [\"batsford\",\"coventry\",\"cumbria\",\"devon\",\"dorset\",\"glencoe\",\"hope-valley\",\"kenilworth\",\"lake- district\",\"norfolk\",\"northumbria\",\"solihull\",\"somerset\",\"suffolk\",\"warwickshire\",\"worcestershire\",\"yorkshire\",\"wales\",\"residential\",\"ireland\"];\n\n\n.custom-filter-container.custom-filter-view-dropdowns .customFiltersWrapper .sqs-block {\n  max-width: 33.33%\n  }\n\nwindow.customFilterSettings = {\n    'targets': [{\n            container: '.sqs-events-collection-list, #block-yui_3_17_2_1_1521549855177_44542,#block-yui_3_17_2_1_1564902899455_5204,#collection-53d39321e4b009befdb652c8 .ProductList,#collection-5eb7c3a098232c36f5d347d5 .ProductList',\n            items: '.eventlist-event--upcoming, .summary-item, .ProductList-item',\n            settings: {\n                placeFiltersTo: '.placeFilters',\n                position: 'top',\n                showItemsCount: true,\n                customClasses: '',\n                align: 'center',\n                useHistory: true,\n                updateFilterOptions: {\n                    enabled: true,\n                    nonExistOptions: {\n                        hide: false,\n                        disable: false,\n                        disableHard: false\n                    },\n                    showOptionsCounters: true,\n                    optionsCounterWrap: '- ()',\n                },\n                //keepDropdownsOpen: true,\n                simpleFilter: {\n                    show: {\n                        effect: 'fade',\n                        transitionDuration: 300,\n                        stagger: 30\n                    },\n                    hide: {\n                        effect: 'fade',\n                        transitionDuration: 100,\n                        stagger: 18\n                    }\n                },\n                hooks: {\n                    beforeCreate: function(target) {\n                        if (location.pathname.indexOf('/photography-shop') > -1 || location.pathname.indexOf('/photography-services') > -1) {\n                            target.settings.filter = {\n                                category: false,\n                                tag: false,\n                                items: [{\n                                        name: 'Categories',\n                                        multiple: true,\n                                        getAttr: 'categories'\n                                    },\n                                    {\n                                        name: 'Tag',\n                                        multiple: true,\n                                        notAllowedOptions: locations,\n                                        getAttr: 'tags'\n                                    },\n                                    {\n                                        name: 'Location',\n                                        multiple: false,\n                                        allowedOptions: locations,\n                                        getAttr: 'tags'\n                                    },\n                                ]\n                            }\n                        }\n                        if (location.pathname.indexOf('workshops') > -1) {\n                            target.settings.filter = {\n                                category: false,\n                                tag: false,\n                                items: [{\n                                        name: 'Workshops Location',\n                                        multiple: false,\n                                        getAttr: function(el, data) {\n                                            if (data && data.location && data.location.addressTitle) {\n                                                return data.location.addressTitle;\n                                            }\n                                            return false;\n                                        }\n                                    },\n                                    {\n                                        name: 'Workshops Duration',\n                                        multiple: true,\n                                        getAttr: 'categories'\n                                    }, {\n                                        name: 'Workshops Year',\n                                        multiple: false,\n                                        getAttr: function(it, data) {\n                                            it = it._node || it;\n                                            var time = it.querySelector('[datetime]');\n                                            if (time) {\n                                                time = time.getAttribute('datetime').substr(0, 4);\n                                                return time;\n                                            } else if (data && data.startDate) {\n                                                return new Date(data.startDate).getFullYear()\n                                            }\n                                        }\n                                    },\n                                    {\n                                        name: 'Workshops Month',\n                                        multiple: false,\n                                        allowedOptions: monthNames,\n                                        sort: 'asAllowed',\n                                        getAttr: function(it, data) {\n                                            it = it._node || it;\n                                            var time = it.querySelector('[datetime]');\n                                            if (time) {\n                                                time = new Date(time.getAttribute('datetime')).toLocaleString('default', { month: 'long' });\n                                                return time;\n                                            } else if (data && data.startDate) {\n                                                return new Date(data.startDate).toLocaleString('default', { month: 'long' });\n                                            }\n                                        }\n                                    },\n                                    {\n                                        name: 'Tag',\n                                        multiple: true,\n                                        getAttr: 'tags'\n                                    }\n                                ]\n                            }\n                        }\n                        if (location.pathname.indexOf('course') > -1 || location.pathname.indexOf('classes') > -1) {\n                            target.settings.filter = {\n                                category: false,\n                                tag: false,\n                                items: [{\n                                        name: 'Courses Location',\n                                        multiple: true,\n                                        getAttr: function(el, data) {\n                                            if (data && data.location && data.location.addressTitle) {\n                                                return data.location.addressTitle;\n                                            }\n                                            return false;\n                                        }\n                                    },\n                                    {\n                                        name: 'Courses Categories',\n                                        multiple: true,\n                                        getAttr: 'categories'\n                                    }, {\n                                        name: 'Courses Year',\n                                        multiple: false,\n                                        getAttr: function(it, data) {\n                                            it = it._node || it;\n                                            var time = it.querySelector('[datetime]');\n                                            if (time) {\n                                                time = time.getAttribute('datetime').substr(0, 4);\n                                                return time;\n                                            } else if (data && data.startDate) {\n                                                return new Date(data.startDate).getFullYear()\n                                            }\n                                        }\n                                    }, {\n                                        name: 'Courses Month',\n                                        multiple: false,\n                                        allowedOptions: monthNames,\n                                        sort: 'asAllowed',\n                                        getAttr: function(it, data) {\n                                            it = it._node || it;\n                                            var time = it.querySelector('[datetime]');\n                                            if (time) {\n                                                time = new Date(time.getAttribute('datetime')).toLocaleString('default', { month: 'long' });\n                                                return time;\n                                            } else if (data && data.startDate) {\n                                                return new Date(data.startDate).toLocaleString('default', { month: 'long' });\n                                            }\n                                        }\n                                    }, {\n                                        name: 'Tag',\n                                        multiple: true,\n                                        getAttr: 'tags'\n                                    }\n                                ]\n                            }\n                        }\n                        if (location.pathname.indexOf('/photographic-workshops') > -1) {\n                            target.settings.position = 'top';\n                            //target.settings.customIndexUrl = '/workshops-events-custom-index';\n                        } else if (location.pathname.indexOf('/photography-classes') > -1) {\n                            target.settings.position = 'top';\n                            //target.settings.customIndexUrl = '/classes-events-custom-index';\n                        }\n                    }\n                },\n                sort: {\n                    items: [{\n                            name: 'A-Z',\n                            order: 'asc',\n                            sort: function(el, data) {\n                                if (data) {\n                                    return data.title;\n                                }\n                            }\n                        },\n                        {\n                            name: 'Z-A',\n                            order: 'desc',\n                            sort: function(el, data) {\n                                if (data) {\n                                    return data.title;\n                                }\n                            }\n                        },\n                        {\n                            name: 'Date',\n                            order: 'asc|desc',\n                            sort: function(el, data) {\n                                var result = 1;\n                                if (data && data.id) {\n                                    result = data.startDate;\n                                }\n                                return result;\n                            }\n                        }\n                    ]\n                }\n            }\n        },\n        {\n            container: '#collection-53836c32e4b05b1c55576880 .BlogList, #block-yui_3_17_2_1_1529137402624_4143',\n            items: '.hentry, .summary-item',\n            settings: {\n                //placeFiltersTo: '.collection-header',\n                position: 'top',\n                useSessionCache: false,\n                showItemsCount: true,\n                useHistory: true,\n                //keepDropdownsOpen: true,\n                updateFilterOptions: {\n                    enabled: true,\n                    nonExistOptions: {\n                        hide: false,\n                        disable: false,\n                        disableHard: false\n                    },\n                    showOptionsCounters: true,\n                    optionsCounterWrap: '- ()',\n                },\n                hooks: {\n                    beforeCreate: function(target) {\n                        if (window.top && window.top.Static && window.top.Static.IN_BACKEND) {\n                            target.noNeedCreate = true;\n                        }\n                    },\n                    beforeInit: function(filter) {\n                        //console.log(filter.target.settings)\n                        if (Y.one('body').hasClass('view-list')) {\n                            //filter.target.settings.customIndexUrl = '/blog-blog-custom-index';\n                        }\n                    },\n                    onInit: function(filter) {\n                        filter.target.settings.pagination.loadMoreButton.enabled = false;\n                    }\n                },\n                simpleFilter: {\n                    show: {\n                        effect: 'fade',\n                        transitionDuration: 300,\n                        stagger: 30\n                    },\n                    hide: {\n                        effect: 'fade',\n                        transitionDuration: 100,\n                        stagger: 18\n                    }\n                },\n                sort: {\n                    items: [{\n                        name: 'A-Z',\n                        order: 'asc',\n                        sort: function(el, data) {\n                            var title = '';\n                            if (data) {\n                                title = data.title;\n                            }\n                            return title;\n                        }\n                    }, {\n                        name: 'Z-A',\n                        order: 'desc',\n                        sort: function(el, data) {\n                            var title = '';\n                            if (data) {\n                                title = data.title;\n                            }\n                            return title;\n                        }\n                    }, {\n                        name: 'Date',\n                        order: 'asc|desc',\n                        sort: function(el, data) {\n                            var result = 1;\n                            if (data && data.id) {\n                                result = data.publishOn;\n                            }\n                            return result;\n                        }\n                    }]\n                },\n                pagination: {\n                    enabled: true,\n                    pageSize: 8,\n                    place: \"bottom\",\n                    showPrevNext: { //will show next/prev elements arrows\n                        enabled: true,\n                        //hideItems: true,\n                        next: 'Next', //next link text\n                        prev: 'Prev' //previous link text\n                    },\n                    loadMoreButton: {\n                        enabled: false\n                    }\n                },\n                filter: {\n                    category: false,\n                    tag: false,\n                    items: [{\n                        name: 'Category',\n                        multiple: true,\n                        getAttr: 'categories'\n                    }, {\n                        name: 'Tag',\n                        multiple: true,\n                        getAttr: 'tags'\n                    }]\n                }\n            }\n        }\n    ]\n};\n\n\n\n\n\n\n\n!function(){window.self===window.top||window.document.getElementById(\"sqstp-UI-theme-script\")||function(e,t,s,i,a){if(s.querySelector(\"#\"+t))i&&i(this);else{var n=document.createElement(\"script\");n.src=e+\"?cache=\"+((new Date).getTime()+\"\").substr(0,8),n.async=!0,n.id=t,n.onload=function(){a&&this.remove(),i&&i(this)},s.appendChild(n)}}(\"https://plugins.squarewebsites.org/sqstools-ext/themes/modern.min.js\",\"sqstp-UI-theme-script\",window.document.getElementsByTagName(\"head\")[0])}();\n\n\n\n\n\n\n\n$( \".reading-time\" ).insertBefore( \"h1.BlogItem-title\" );\n\n\n\n\n\n  var scrolled = 400; $(window).scroll(function() {\n    if ( $(window).scrollTop() > scrolled ) {\n      $('a.btt').fadeIn('slow');\n    } else {\n      $('a.btt').fadeOut('slow');\n    }\n  });\n\n\n  $('a.btt').click(function() {\n    $('html, body').animate({ scrollTop: 0 }, 700);\n    return false;\n  });\n\n\n\n\n$(document).ready(function () {\n    // Define the hover timeout duration in milliseconds\n    var hoverTimeoutDuration = 3000; // Example: 3000ms (3 seconds)\n\n    $('.Header-nav-folder-title[href^=\"/mega-\"]').each(function () {\n        var e = $(this).attr(\"href\").slice(6);\n        $(this).parent().addClass(\"mega-menu\");\n        var a = $(this).closest(\"header.Header\");\n        a.append(\"<div id=\" + e + ' class=\"mega-menu-item\"></div>');\n        $(\"#\" + e).load(\"/mega-menu-pages #mega-page-\" + e, function () {\n            window.Squarespace.initializeLayoutBlocks(Y, Y.one(\"#\" + e));\n            var imgs = document.querySelectorAll(\".mega-menu-item img[data-src]\");\n            for (var n = 0; n < imgs.length; n++) {\n                ImageLoader.load(imgs[n], { load: true, fill: true });\n                imgs[n].parentNode.className += \" loaded\";\n            }\n        });\n        var hoverTimeout;\n        // Function to start hover timeout\n        function startHoverTimeout() {\n            clearTimeout(hoverTimeout);\n            hoverTimeout = setTimeout(function () {\n                removeHoverFromAll();\n            }, hoverTimeoutDuration);\n        }\n        // Function to remove hover from all mega menus\n        function removeHoverFromAll() {\n            $('.mega-menu-item').removeClass('hover');\n            $('.mega-menu').removeClass('hover');\n        }\n        // Handle hover on the link's parent\n        $(this).parent().hover(\n            function () {\n                removeHoverFromAll(); // Remove hover from all other mega menus\n                a.find(\"#\" + e).addClass(\"hover\");\n                clearTimeout(hoverTimeout);\n                // Monitor mouse movement to reset hover timeout\n                $(document).on(\"mousemove.megaMenu\", function () {\n                    clearTimeout(hoverTimeout);\n                    startHoverTimeout();\n                });\n            },\n            function () {\n                startHoverTimeout();\n                $(document).off(\"mousemove.megaMenu\");\n            }\n        );\n        // Handle hover on the mega menu content\n        $(\"#\" + e).hover(\n            function () {\n                a.find(\"#\" + e).addClass(\"hover\");\n                clearTimeout(hoverTimeout);\n\n                // Monitor mouse movement to reset hover timeout\n                $(document).on(\"mousemove.megaMenuContent\", function () {\n                    clearTimeout(hoverTimeout);\n                    startHoverTimeout();\n                });\n            },\n            function () {\n                startHoverTimeout();\n                $(document).off(\"mousemove.megaMenuContent\");\n            }\n        );\n        // Detect hover on anything outside the mega menu or its link\n        $(\"body\").on(\"mouseenter\", \"","excerpt":"Get a camera sensor clean in Coventry . Sensor checked and cleaned using professional equipment, swabs | Full Frame and Cropped Sensors | 24hr Turnaround","end_date":null,"start_time":null,"end_time":null,"location_city_state_zip":null,"image_url":null,"json_ld_data":{"url":"https://www.alanranger.com/photography-services-near-me/camera-sensor-clean","name":"Professional Digital DSLR Camera Sensor Clean | Coventry","@type":"Product","image":"https://images.squarespace-cdn.com/content/v1/5013f4b2c4aaa4752ac69b17/1522495201980-KD6BKH54J01HJR93XXR6/photography-support-Services-1.png","offers":{"@type":"Offer","price":30,"availability":"http://schema.org/InStock","priceCurrency":"GBP","shippingDetails":{"@type":"OfferShippingDetails","doesNotShip":"http://schema.org/True","shippingDestination":{"@type":"DefinedRegion","addressCountry":"GB"}},"hasMerchantReturnPolicy":{"@type":"MerchantReturnPolicy","refundType":"http://schema.org/FullRefund","returnFees":"http://schema.org/FreeReturn","returnMethod":"http://schema.org/ReturnByMail","applicableCountry":"GB","merchantReturnDays":28,"returnPolicyCategory":"http://schema.org/MerchantReturnFiniteReturnWindow"}},"@context":"https://schema.org/","description":"Get a camera sensor clean in Coventry . Sensor checked and cleaned using professional equipment, swabs | Full Frame and Cropped Sensors | 24hr Turnaround"},"workflow_state":null,"participants":null,"experience_level":null,"equipment_needed":null,"time_schedule":null,"fitness_level":null,"what_to_bring":null,"course_duration":"in milliseconds","instructor_info":null,"availability_status":null,"meta_description":"Get a camera sensor clean in Coventry . Sensor checked and cleaned using professional equipment, swabs | Full Frame and Cropped Sensors | 24hr Turnaround","csv_metadata":{"kind":"service","title":null}},{"id":257704,"url":"https://www.alanranger.com/photo-workshops-uk","kind":"event","title":"Photo Workshops Uk","description":"PHOTO WORKSHOPS UK | LANDSCAPE PHOTOGRAPHY WORKSHOPS","date_start":null,"date_end":null,"location":null,"price":null,"price_currency":null,"availability":null,"sku":null,"provider":"Alan Ranger Photography","source_url":"https://www.alanranger.com/photo-workshops-uk","raw":{"name":"Alan Ranger Photography","@type":"LocalBusiness","image":"https://static1.squarespace.com/static/5013f4b2c4aaa4752ac69b17/t/6749dba3f5275a74ca88a3bd/1761580471344/","address":"45 Hathaway Road\nCoventry, England, CV4 9HW\nUnited Kingdom","@context":"http://schema.org","openingHours":"Mo 09:00-17:00, Tu 09:00-17:00, We 09:00-17:00, Th 09:00-17:00, Fr 09:00-17:00, Sa 09:00-17:00, Su 09:00-17:00","_csv_end_time":null,"_csv_start_time":null},"entity_hash":"9e0216828fc7f180bb0168df0d1dcbc31e7b1f76","last_seen":"2025-10-29T18:30:47.194+00:00","page_url":"https://www.alanranger.com/photo-workshops-uk","norm_title":"alan ranger photography","start_date":null,"csv_type":"landing_service_pages","csv_metadata_id":70631,"categories":null,"tags":null,"publish_date":null,"location_name":null,"location_address":null,"excerpt":null,"end_date":null,"start_time":null,"end_time":null,"location_city_state_zip":null,"image_url":null,"json_ld_data":null,"workflow_state":null,"participants":null,"experience_level":null,"equipment_needed":null,"time_schedule":null,"fitness_level":null,"what_to_bring":null,"course_duration":"in milliseconds","instructor_info":null,"availability_status":null,"meta_description":null,"csv_metadata":{"kind":"service","title":null}},{"id":244487,"url":"https://www.alanranger.com/photography-mentoring-online-assignments","kind":"service","title":"Photography Mentoring Online - Monthly Assignments","description":"UK Landscape Photography Workshops, Beginners Courses and Private Lessons - Enhance your skill with Alan Ranger Photography - Qualified Tutor and Professional Photographer","date_start":null,"date_end":null,"location":null,"price":null,"price_currency":null,"availability":null,"sku":null,"provider":"Alan Ranger Photography","source_url":"https://www.alanranger.com/photography-mentoring-online-assignments","raw":{"url":"https://www.alanranger.com","name":"Alan Ranger Photography","@type":"WebSite","image":"//images.squarespace-cdn.com/content/v1/5013f4b2c4aaa4752ac69b17/b859ad2b-1442-4595-b9a4-410c32299bf8/ALAN+RANGER+photography+LOGO+BLACK.+switched+small.png","@context":"http://schema.org","description":"<p class=\"\" style=\"white-space:pre-wrap;\">UK Landscape Photography Workshops,&nbsp;Beginners Courses and Private Lessons - Enhance your skill with Alan Ranger Photography - Qualified Tutor and Professional Photographer</p>"},"entity_hash":"330a86fe9b5f75e82670c1620f045d3b679eaa10","last_seen":"2025-10-29T17:53:41.231+00:00","page_url":"https://www.alanranger.com/photography-mentoring-online-assignments","norm_title":"photography mentoring online - monthly assignments","start_date":null,"csv_type":"landing_service_pages","csv_metadata_id":70600,"categories":null,"tags":null,"publish_date":null,"location_name":null,"location_address":".pathname.indexOf('/photography-services') > -1) {","excerpt":null,"end_date":null,"start_time":null,"end_time":null,"location_city_state_zip":null,"image_url":null,"json_ld_data":null,"workflow_state":null,"participants":null,"experience_level":null,"equipment_needed":"Equipment necessaryDigital CameraComputerInternet connection and Dropbox","time_schedule":"Online - Zoom","fitness_level":null,"what_to_bring":null,"course_duration":"in milliseconds","instructor_info":null,"availability_status":null,"meta_description":"Photography mentoring online sessions - Monthly Assignments to expand your skills and experience and help you grow and diversify your knowledge.  Join Today.","csv_metadata":{"kind":"service","title":null}},{"id":244506,"url":"https://www.alanranger.com/photography-workshops","kind":"service","title":"Best UK Outdoor Landscape Photography Workshops | Book Now","description":"UK Landscape Photography Workshops, Beginners Courses and Private Lessons - Enhance your skill with Alan Ranger Photography - Qualified Tutor and Professional Photographer","date_start":null,"date_end":null,"location":null,"price":null,"price_currency":null,"availability":null,"sku":null,"provider":"Alan Ranger Photography","source_url":"https://www.alanranger.com/photography-workshops","raw":{"url":"https://www.alanranger.com","name":"Alan Ranger Photography","@type":"WebSite","image":"//images.squarespace-cdn.com/content/v1/5013f4b2c4aaa4752ac69b17/b859ad2b-1442-4595-b9a4-410c32299bf8/ALAN+RANGER+photography+LOGO+BLACK.+switched+small.png","@context":"http://schema.org","description":"<p class=\"\" style=\"white-space:pre-wrap;\">UK Landscape Photography Workshops,&nbsp;Beginners Courses and Private Lessons - Enhance your skill with Alan Ranger Photography - Qualified Tutor and Professional Photographer</p>"},"entity_hash":"b78f7423d579473648a82aaf32211681488142ff","last_seen":"2025-10-29T17:53:37.585+00:00","page_url":"https://www.alanranger.com/photography-workshops","norm_title":"best uk outdoor landscape photography workshops | book now","start_date":null,"csv_type":"landing_service_pages","csv_metadata_id":70602,"categories":null,"tags":null,"publish_date":null,"location_name":null,"location_address":".","excerpt":null,"end_date":null,"start_time":null,"end_time":null,"location_city_state_zip":null,"image_url":null,"json_ld_data":null,"workflow_state":null,"participants":null,"experience_level":null,"equipment_needed":null,"time_schedule":"out duration in milliseconds","fitness_level":null,"what_to_bring":null,"course_duration":"in milliseconds","instructor_info":". Something that doesnâ??t always come hand in handâ?","availability_status":null,"meta_description":"Join our top-rated landscape photography workshops across the UK. Perfect for beginners and intermediates. Book now for expert tuition in stunning locations!","csv_metadata":{"kind":"service","title":null}},{"id":244565,"url":"https://www.alanranger.com/photography-lessons-online-121","kind":"service","title":"Learn Photography from Home | Photography Lessons Online","description":"UK Landscape Photography Workshops, Beginners Courses and Private Lessons - Enhance your skill with Alan Ranger Photography - Qualified Tutor and Professional Photographer","date_start":null,"date_end":null,"location":null,"price":null,"price_currency":null,"availability":null,"sku":null,"provider":"Alan Ranger Photography","source_url":"https://www.alanranger.com/photography-lessons-online-121","raw":{"url":"https://www.alanranger.com","name":"Alan Ranger Photography","@type":"WebSite","image":"//images.squarespace-cdn.com/content/v1/5013f4b2c4aaa4752ac69b17/b859ad2b-1442-4595-b9a4-410c32299bf8/ALAN+RANGER+photography+LOGO+BLACK.+switched+small.png","@context":"http://schema.org","description":"<p class=\"\" style=\"white-space:pre-wrap;\">UK Landscape Photography Workshops,&nbsp;Beginners Courses and Private Lessons - Enhance your skill with Alan Ranger Photography - Qualified Tutor and Professional Photographer</p>"},"entity_hash":"d00a51fd9f73a27fb6a2f5c0d91768cd4add219a","last_seen":"2025-10-29T17:53:37.328+00:00","page_url":"https://www.alanranger.com/photography-lessons-online-121","norm_title":"learn photography from home | photography lessons online","start_date":null,"csv_type":"landing_service_pages","csv_metadata_id":70598,"categories":null,"tags":null,"publish_date":null,"location_name":null,"location_address":".pathname.indexOf('/photography-services') > -1) {","excerpt":null,"end_date":null,"start_time":null,"end_time":null,"location_city_state_zip":null,"image_url":null,"json_ld_data":null,"workflow_state":null,"participants":null,"experience_level":null,"equipment_needed":null,"time_schedule":"Online - Zoom","fitness_level":null,"what_to_bring":null,"course_duration":"in milliseconds","instructor_info":null,"availability_status":".","meta_description":"Enhance Your Photography Skills with Zoom Photography Lessons Online. Learn Camera Settings and Photo Editing Techniques.  All on 1-2-1 Basis - Join Now!","csv_metadata":{"kind":"service","title":null}},{"id":244488,"url":"https://www.alanranger.com/photography-payment-plan","kind":"service","title":"Pick N Mix Photography Payment Plan - Tuition Packages","description":"UK Landscape Photography Workshops, Beginners Courses and Private Lessons - Enhance your skill with Alan Ranger Photography - Qualified Tutor and Professional Photographer","date_start":null,"date_end":null,"location":null,"price":null,"price_currency":null,"availability":null,"sku":null,"provider":"Alan Ranger Photography","source_url":"https://www.alanranger.com/photography-payment-plan","raw":{"url":"https://www.alanranger.com","name":"Alan Ranger Photography","@type":"WebSite","image":"//images.squarespace-cdn.com/content/v1/5013f4b2c4aaa4752ac69b17/b859ad2b-1442-4595-b9a4-410c32299bf8/ALAN+RANGER+photography+LOGO+BLACK.+switched+small.png","@context":"http://schema.org","description":"<p class=\"\" style=\"white-space:pre-wrap;\">UK Landscape Photography Workshops,&nbsp;Beginners Courses and Private Lessons - Enhance your skill with Alan Ranger Photography - Qualified Tutor and Professional Photographer</p>"},"entity_hash":"52794883ee48c9fc54f2c3b3220f3bcec6961610","last_seen":"2025-10-29T17:53:36.738+00:00","page_url":"https://www.alanranger.com/photography-payment-plan","norm_title":"pick n mix photography payment plan - tuition packages","start_date":null,"csv_type":"landing_service_pages","csv_metadata_id":70609,"categories":null,"tags":null,"publish_date":null,"location_name":null,"location_address":".pathname.indexOf('/photography-services') > -1) {","excerpt":null,"end_date":null,"start_time":null,"end_time":null,"location_city_state_zip":null,"image_url":null,"json_ld_data":null,"workflow_state":null,"participants":null,"experience_level":null,"equipment_needed":null,"time_schedule":"out duration in milliseconds","fitness_level":null,"what_to_bring":null,"course_duration":"in milliseconds","instructor_info":null,"availability_status":null,"meta_description":"Photography Payment Plan - Photography Tuition packages pick n mix - Choose courses, workshops or 1-2-1s The payment is interest free and spread over 12 months","csv_metadata":{"kind":"service","title":null}},{"id":244472,"url":"https://www.alanranger.com/private-photography-lessons","kind":"service","title":"Private Photography Lessons Near Me - Face to Face Coventry","description":"UK Landscape Photography Workshops, Beginners Courses and Private Lessons - Enhance your skill with Alan Ranger Photography - Qualified Tutor and Professional Photographer","date_start":null,"date_end":null,"location":null,"price":null,"price_currency":null,"availability":null,"sku":null,"provider":"Alan Ranger Photography","source_url":"https://www.alanranger.com/private-photography-lessons","raw":{"url":"https://www.alanranger.com","name":"Alan Ranger Photography","@type":"WebSite","image":"//images.squarespace-cdn.com/content/v1/5013f4b2c4aaa4752ac69b17/b859ad2b-1442-4595-b9a4-410c32299bf8/ALAN+RANGER+photography+LOGO+BLACK.+switched+small.png","@context":"http://schema.org","description":"<p class=\"\" style=\"white-space:pre-wrap;\">UK Landscape Photography Workshops,&nbsp;Beginners Courses and Private Lessons - Enhance your skill with Alan Ranger Photography - Qualified Tutor and Professional Photographer</p>"},"entity_hash":"937264ec9b50f46728f8ea0a6b9774d6db32d0d8","last_seen":"2025-10-29T17:53:36.671+00:00","page_url":"https://www.alanranger.com/private-photography-lessons","norm_title":"private photography lessons near me - face to face coventry","start_date":null,"csv_type":"landing_service_pages","csv_metadata_id":70599,"categories":null,"tags":null,"publish_date":null,"location_name":null,"location_address":"of your choice for your lesson.","excerpt":null,"end_date":null,"start_time":null,"end_time":null,"location_city_state_zip":null,"image_url":null,"json_ld_data":null,"workflow_state":null,"participants":null,"experience_level":null,"equipment_needed":null,"time_schedule":"Face-to-Face Coventry or your location","fitness_level":null,"what_to_bring":null,"course_duration":"in milliseconds","instructor_info":null,"availability_status":null,"meta_description":"Face to face private photography lessons near me in Coventry are taught at the pace of the individual. Combine theory and practice with a professional tutor","csv_metadata":{"kind":"service","title":null}},{"id":244470,"url":"https://www.alanranger.com/photography-gift-vouchers","kind":"service","title":"Photography Gift Vouchers - Buy Online Use against any event","description":"UK Landscape Photography Workshops, Beginners Courses and Private Lessons - Enhance your skill with Alan Ranger Photography - Qualified Tutor and Professional Photographer","date_start":null,"date_end":null,"location":null,"price":null,"price_currency":null,"availability":null,"sku":null,"provider":"Alan Ranger Photography","source_url":"https://www.alanranger.com/photography-gift-vouchers","raw":{"url":"https://www.alanranger.com","name":"Alan Ranger Photography","@type":"WebSite","image":"//images.squarespace-cdn.com/content/v1/5013f4b2c4aaa4752ac69b17/b859ad2b-1442-4595-b9a4-410c32299bf8/ALAN+RANGER+photography+LOGO+BLACK.+switched+small.png","@context":"http://schema.org","description":"<p class=\"\" style=\"white-space:pre-wrap;\">UK Landscape Photography Workshops,&nbsp;Beginners Courses and Private Lessons - Enhance your skill with Alan Ranger Photography - Qualified Tutor and Professional Photographer</p>"},"entity_hash":"dd450e09d22a5da0d5448665bcb1269275f28e63","last_seen":"2025-10-29T17:53:36.439+00:00","page_url":"https://www.alanranger.com/photography-gift-vouchers","norm_title":"photography gift vouchers - buy online use against any event","start_date":null,"csv_type":"landing_service_pages","csv_metadata_id":70606,"categories":null,"tags":null,"publish_date":null,"location_name":null,"location_address":".pathname.indexOf('/photography-services') > -1) {","excerpt":null,"end_date":null,"start_time":null,"end_time":null,"location_city_state_zip":null,"image_url":null,"json_ld_data":null,"workflow_state":null,"participants":null,"experience_level":null,"equipment_needed":null,"time_schedule":"out duration in milliseconds","fitness_level":null,"what_to_bring":null,"course_duration":"in milliseconds","instructor_info":null,"availability_status":null,"meta_description":"Photography Gift Vouchers - The Perfect Present for Any Enthusiast | Voucher Redeemable for Private Tuition, Lessons, Workshops, and More - Buy Online Today.","csv_metadata":{"kind":"service","title":null}},{"id":244537,"url":"https://www.alanranger.com/landscape-photography-workshops","kind":"service","title":"Landscape Photography Workshops UK â?? Inspiring Locations","description":"UK Landscape Photography Workshops, Beginners Courses and Private Lessons - Enhance your skill with Alan Ranger Photography - Qualified Tutor and Professional Photographer","date_start":null,"date_end":null,"location":null,"price":null,"price_currency":null,"availability":null,"sku":null,"provider":"Alan Ranger Photography","source_url":"https://www.alanranger.com/landscape-photography-workshops","raw":{"url":"https://www.alanranger.com","name":"Alan Ranger Photography","@type":"WebSite","image":"//images.squarespace-cdn.com/content/v1/5013f4b2c4aaa4752ac69b17/b859ad2b-1442-4595-b9a4-410c32299bf8/ALAN+RANGER+photography+LOGO+BLACK.+switched+small.png","@context":"http://schema.org","description":"<p class=\"\" style=\"white-space:pre-wrap;\">UK Landscape Photography Workshops,&nbsp;Beginners Courses and Private Lessons - Enhance your skill with Alan Ranger Photography - Qualified Tutor and Professional Photographer</p>"},"entity_hash":"e14f49155d68224cfd8b85ac8b10eee8cf3cbe5d","last_seen":"2025-10-29T17:53:24.51+00:00","page_url":"https://www.alanranger.com/landscape-photography-workshops","norm_title":"landscape photography workshops uk â?? inspiring locations","start_date":null,"csv_type":"landing_service_pages","csv_metadata_id":70603,"categories":null,"tags":null,"publish_date":null,"location_name":null,"location_address":"s2025 - 2026 Photo Workshops - 2.5 Hrs to 4 Hrs","excerpt":null,"end_date":null,"start_time":null,"end_time":null,"location_city_state_zip":null,"image_url":null,"json_ld_data":null,"workflow_state":null,"participants":null,"experience_level":null,"equipment_needed":null,"time_schedule":"out duration in milliseconds","fitness_level":null,"what_to_bring":null,"course_duration":"in milliseconds","instructor_info":null,"availability_status":null,"meta_description":"Master landscape photography in real UK locations. Small-group workshops with expert tutor Alan Ranger â?? practical, inspiring, and tailored to all levels.","csv_metadata":{"kind":"service","title":null}},{"id":244567,"url":"https://www.alanranger.com/free-online-photography-course","kind":"service","title":"Free Online Photography Course - Online Photography Academy","description":"UK Landscape Photography Workshops, Beginners Courses and Private Lessons - Enhance your skill with Alan Ranger Photography - Qualified Tutor and Professional Photographer","date_start":null,"date_end":null,"location":null,"price":null,"price_currency":null,"availability":null,"sku":null,"provider":"Alan Ranger Photography","source_url":"https://www.alanranger.com/free-online-photography-course","raw":{"url":"https://www.alanranger.com","name":"Alan Ranger Photography","@type":"WebSite","image":"//images.squarespace-cdn.com/content/v1/5013f4b2c4aaa4752ac69b17/b859ad2b-1442-4595-b9a4-410c32299bf8/ALAN+RANGER+photography+LOGO+BLACK.+switched+small.png","@context":"http://schema.org","description":"<p class=\"\" style=\"white-space:pre-wrap;\">UK Landscape Photography Workshops,&nbsp;Beginners Courses and Private Lessons - Enhance your skill with Alan Ranger Photography - Qualified Tutor and Professional Photographer</p>"},"entity_hash":"8893be56b37716f589d42d14cf8d4f64b2553c42","last_seen":"2025-10-29T17:53:24.377+00:00","page_url":"https://www.alanranger.com/free-online-photography-course","norm_title":"free online photography course - online photography academy","start_date":null,"csv_type":"landing_service_pages","csv_metadata_id":70591,"categories":null,"tags":null,"publish_date":null,"location_name":null,"location_address":"Where to find subjects and when to shoot","excerpt":null,"end_date":null,"start_time":null,"end_time":null,"location_city_state_zip":null,"image_url":null,"json_ld_data":null,"workflow_state":null,"participants":null,"experience_level":null,"equipment_needed":null,"time_schedule":"out duration in milliseconds","fitness_level":null,"what_to_bring":null,"course_duration":"in milliseconds","instructor_info":null,"availability_status":null,"meta_description":"Free online photography course from the Alan Ranger photography academy. 60 Modules - Camera settings, gear, composition, genres and photo practical exercises","csv_metadata":{"kind":"service","title":null}},{"id":244521,"url":"https://www.alanranger.com/beginners-photography-classes","kind":"service","title":"Beginners Photography Classes - 3 Weekly Evening Classes","description":"UK Landscape Photography Workshops, Beginners Courses and Private Lessons - Enhance your skill with Alan Ranger Photography - Qualified Tutor and Professional Photographer","date_start":null,"date_end":null,"location":null,"price":null,"price_currency":null,"availability":null,"sku":null,"provider":"Alan Ranger Photography","source_url":"https://www.alanranger.com/beginners-photography-classes","raw":{"url":"https://www.alanranger.com","name":"Alan Ranger Photography","@type":"WebSite","image":"//images.squarespace-cdn.com/content/v1/5013f4b2c4aaa4752ac69b17/b859ad2b-1442-4595-b9a4-410c32299bf8/ALAN+RANGER+photography+LOGO+BLACK.+switched+small.png","@context":"http://schema.org","description":"<p class=\"\" style=\"white-space:pre-wrap;\">UK Landscape Photography Workshops,&nbsp;Beginners Courses and Private Lessons - Enhance your skill with Alan Ranger Photography - Qualified Tutor and Professional Photographer</p>"},"entity_hash":"fa732234612b36294fd11899e53a76bc51b02c64","last_seen":"2025-10-29T17:53:24.157+00:00","page_url":"https://www.alanranger.com/beginners-photography-classes","norm_title":"beginners photography classes - 3 weekly evening classes","start_date":null,"csv_type":"landing_service_pages","csv_metadata_id":70595,"categories":null,"tags":null,"publish_date":null,"location_name":null,"location_address":"45 Hathaway Road, Tile Hill Village, Coventry, CV4 9HWParticipants: Max 4Time: 19:00 - 21:00Multi Course Start","excerpt":null,"end_date":null,"start_time":null,"end_time":null,"location_city_state_zip":null,"image_url":null,"json_ld_data":null,"workflow_state":null,"participants":"4","experience_level":"Beginner and Novice","equipment_needed":"You will need a DSLR or Mirrorless Camera with manual exposure modes.Alan will provide you with a course book covering all the topics for the course","time_schedule":"19:00 - 21:00Multi Course Start Dates: Beginners Photography Course3wks Mondays - Sep 8 - 22 Sep Coventry3wks Thursdays - Sep 11 - 25 Sep Coventry3wks Thursdays - Oct 2 - Oct 16 Coventry3wks Mondays - Oct 6 - Oct 20 Coventry3wks Mondays - Nov 3 - Nov 17 Coventry3wks Wednesdays - Nov 12 - Nov 26 Coventry3wks Tuesdays - Dec 2 - Dec 16 Coventry3wks Tuesdays - Jan 6 - Jan 20 Coventry3wks Wednesdays - Feb 4 - Feb 18 Coventry3wks Mondays - Mar 9 - Mar 23 CoventryExperience - Level: Beginner and NoviceThis beginners photography course is aimed at anyone with a digital camera wishing to get off auto exposure mode and learn about key camera settings and composition to make better photos.Equipment Needed:You will need a DSLR or Mirrorless Camera with manual exposure modes.Alan will provide you with a course book covering all the topics for the course\n\n          \n          \n            \n\n\n  \n    \n    \n  \n\n  \n    \n      \n        \n          \n            \n              \n                \n                  \n                    Dates:\n                  \n                  \n                    \n                      \n                        Select Dates\n                      \n                      \n                        3wks Mondays - Sep 8 - 22 Sep Coventry\n                      \n                        3wks Thursdays - Sep 11 - Sep 25 Coventry\n                      \n                        3wks Thursdays - Oct 2 - Oct 16 Coventry\n                      \n                        3wks Mondays - Oct 6 - Oct 20 Coventry\n                      \n                        3wks Mondays - Nov 3 - Nov 17 Coventry\n                      \n                        3wks Wednesdays - Nov 12 - Nov 26 Coventry\n                      \n                        3wks Tuesdays - Dec 2 - Dec 16 Coventry\n                      \n                        3wks Tuesdays - Jan 6 - Jan 20 Coventry\n                      \n                        3wks Wednesdays - Feb 4 - Feb 18 Coventry\n                      \n                        3wks Mondays - Mar 9 - Mar 23 Coventry\n                      \n                    \n                    \n                      \n                      \n                    \n                    \n                      \n                        \n                      \n                    \n                  \n                \n              \n            \n          \n        \n      \n    \n  \n\n\n            \n              \n                \n\n  \n\n\n\n  \n    \n      \n        \n          \n            \n              \n            \n          \n        \n        \n        \n          \n            \n              \n            \n          \n        \n      \n      \n        \n        \n      \n    \n  \n\n\n\n\n              \n              \n\n\n  \n    \n      \n        \n          Book\n        \n      \n      \n      \n    \n  \n\n\n            \n            \n\n\n  \n    \n  \n\n  \n    \n  \n    \n  \n    \n  \n    \n  \n    \n  \n    \n      \n        Only 4 available\n      \n    \n  \n    \n      \n        Only 4 available\n      \n    \n  \n    \n      \n        Only 4 available\n      \n    \n  \n    \n      \n        Only 4 available\n      \n    \n  \n    \n      \n        Only 4 available\n      \n    \n  \n\n\n          \n        \n      \n    \n  \n  \n\n\ndocument.querySelector('[data-definition-name=\"website.components.product\"] .product-block').classList.add('is-first-product-block');\n\n\n\n\n  Beginners Photography Classes - Course Structure and ContentOur photography course for beginners consists of three weekly evening sessions, each spanning two hours. Whether you opt for the Monday, Tuesday, Wednesday, or Thursday slot, you'll have the flexibility to accommodate the course into your schedule. \n\n\n\n\n\n\n\n\n\n\n\n\n\n\n\n\n\n\n\n\n\n  \n  \n\n\n\nÂ \n\n\n\n\n\n\n\n\n\n\n\n\n\n\n\n\n\n\n\n\n  \n  \n\n\n\n\n\n\n  \n    \n\n      \n        \n          \n        \n      \n\n      \n        \n          \n            Week 1 - Get off auto\n          \n          \n            \n              \n                \n                \n              \n            \n          \n        \n      \n      \n        \n          Wk 1 Get Off Auto - Beginners Photography ClassesIn the inaugural week of our digital photography course, you'll dive into the essentials of photography, learning how to transition from automatic modes to manual control of your camera settings. Explore the photographic workflow, comprehend the exposure triangle (aperture, ISO, and shutter speed), and uncover composition techniques to enhance your images in our basic photography courses.\n        \n      \n\n      \n        \n      \n\n    \n  \n    \n\n      \n        \n      \n\n      \n        \n          \n            Week 2 - Exposure\n          \n          \n            \n              \n                \n                \n              \n            \n          \n        \n      \n      \n        \n          Week 2: Exposure - Beginners Photography ClassesBuilding upon your knowledge from Week 1 of our photography course, Week 2 hones in on exposure. Revisit exposure concepts, learn about metering, histograms, and exposure compensation in our course. Engage in practical exercises and assignments to refine your exposure skills.\n        \n      \n\n      \n        \n      \n\n    \n  \n    \n\n      \n        \n      \n\n      \n        \n          \n            Week 3 - Camera Settings\n          \n          \n            \n              \n                \n                \n              \n            \n          \n        \n      \n      \n        \n          Week 3: Essential Camera Settings - Beginners Photography ClassesDelve deeper into the critical camera settings that can revolutionize your images in our photography course for beginners. Explore focusing techniques, depth of field, and white balance. Gain a more profound understanding of stops, dynamic range, and bracketing to capture the perfect shot.\n        \n      \n\n      \n        \n      \n\n    \n  \n\nÂ \n\n\n  Throughout this Beginners Photography Classes, you'll have the chance to complete practical assignments, allowing you to apply your newly acquired skills and receive feedback from the tutor. This hands-on approach in our course will reinforce your learning and help you evolve as a photographer in our beginner photography classes.You will need a DSLR camera, with any lens as you work through the different camera modes to transition you to manual exposure and working with the adjustments required in natural light.\n\n\n\n\n\n\n\n\n\n\n\n\n\n\n\n\n\n\n\n\n\n  \n  \n\n\n\nÂ \n\n\n  In Coventry 7 PM to 9 PM - Multiple Start Dates45 Hathaway Road, Tile Hill Village, Coventry, CV4 9HW\n\n\n\n\n\n\n\n\n\n\n\n\n\n\n\n\n\n\n\n\n\n  \n  \n\n\n\nÂ Â \n\n\n\n\n\n\n\n\n\n\n\n\n\n\n\n\n\n\n\n\n  \n  \n\n\n\n\n\n\n  \n    \n\n      \n        \n          \n        \n      \n\n      \n        \n          \n            [equipment-icon] What camera do I need for this course?\n          \n          \n            \n              \n                \n                \n              \n            \n          \n        \n      \n      \n        \n          Any DSLR or Mirrorless digital camera.   It doesnâ??t matter how old it is as long as it has the option to switch exposure modes between, Aperture, Shutter and Manual Exposure.I am happy to advise on models if you are looking to buy something but only after you have booked a place on my course or a 1-2-1 lesson as I will work with you personally to find the best option for your budget an needs, rather than just give a generic answer. \n        \n      \n\n      \n        \n      \n\n    \n  \n    \n\n      \n        \n      \n\n      \n        \n          \n            [about-icon] Why Take Beginners Photography Classes?\n          \n          \n            \n              \n                \n                \n              \n            \n          \n        \n      \n      \n        \n          Photography is more than just pointing and shooting; it's an art that demands technical proficiency and a sharp eye for composition. While you can grasp the photography basics through trial and error, signing up for a photography course for beginners will expedite your learning journey and help you sidestep common pitfalls. Here are some reasons why taking photography lessons is advantageous:Master Camera Settings: Understand the ins and outs of your camera, from automatic modes to manual exposure settings. Gain control over aperture, ISO, and shutter speed to achieve the desired effects in your images.Develop Composition Skills: Learn the principles of composition and how to create visually appealing photographs. Discover how to frame your subjects, balance elements, and use lighting to enhance your images.Expand Your Knowledge: Dive deeper into essential concepts such as exposure, focus, depth of field, and white balance. Understand the technical aspects of photography to unleash your creative potential.Receive Expert Guidance: Benefit from the expertise of a professional tutor who will guide you through the course. Alan Ranger, with his years of experience and passion for photography, will provide valuable insights and feedback to help you improve your skills.Structured Learning: Our beginners photography course is designed to provide a systematic and comprehensive learning experience. Each week, you'll focus on a specific aspect of photography, building upon your knowledge and skills.\n        \n      \n\n      \n        \n      \n\n    \n  \n    \n\n      \n        \n      \n\n      \n        \n          \n            [courses-icon] Summary\n          \n          \n            \n              \n                \n                \n              \n            \n          \n        \n      \n      \n        \n          This beginners photography classes will provide you with all the essential foundations on camera settings, composition and use of your equipment. With theory and practical lessons, together with assignments, you will be a more confident and knowledgeable photographer.Spaces for each course are limited, so make sure to secure your spot early. If you need to change your course date, please notify us at least four weeks in advance. Please note that a rebooking fee may apply for changes made within four weeks of the event date.Additional Opportunities for GrowthOnce you've completed our beginner's photography course, you may be interested in further honing your skills. We offer a range of intermediate masterclasses and courses to help you continue your photography journey:Editing Course with Lightroom for BeginnersRPS Course - Distinction MentoringThese next-step photography courses provide more advanced techniques, in-depth knowledge, and personalised mentoring to help you reach new heights in your photography.\n        \n      \n\n      \n        \n      \n\n    \n  \n\n\n              \n            \n          \n\n        \n      \n\n      \n\n  \n\n    \n\n\n\n\n\n\n\n\n\n\n\n\n\n\n\n\n\n\n\n\n  \n  \n\n\n\n\n\n  \n    \n      Get Access to Free Online Course\n      Sign up with your email address to access the Academy 101 Foundation Photography Course\n    \n    \n      \n        \n          \n            \n          \n            \n              \n              \n              \n                \n                  \n                \n                  First Name\n                  \n                \n              \n                  \n                \n                  Last Name\n                  \n                \n              \n                \n              \n            \n          \n        \n        \n          \n            \n              Email Address\n              \n            \n          \n        \n          \n        \n      \n      \n        \n          \n          Join today\n          \n        \n      \n      \n        \n      \n    \n    We respect your privacy.\n    Thank you! You will receive an email to verify and confirm your subscription to receive updates.  Please ensure you click the confirm button in the email.\n    \n  \n\n\n\n    \n      \n\n        \n          \n            \n              \n                Alan Ranger Photography\n                45 Hathaway Road,\n                Coventry, England, CV4 9HW,\n                United Kingdom\n              \n            \n            \n              +44 781 701 7994\n              info@alanranger.com\n            \n          \n        \n\n        \n          \n            \n              Hours\n              Mon 9am - 5pm\n              Tue 9am - 5pm\n              Wed 9am - 5pm\n              Thu 9am - 5pm\n              Fri 9am - 5pm\n              Sat 9am - 5pm\n              Sun 9am - 5pm\n            \n          \n        \n\n      \n\n      \n\n      \n  \n\n    Contact UsHelp - Site MapFree Online Photography CourseOnline - Zoom LessonsPrivate LessonsPhoto WorkshopsGift VouchersPhotography TipsSchedule an appointment\n\n  \n\n    \n\n    \n\n\n  Proud to be a member of\n\n\n\n\n\n\n\n\n\n\n\n\n\n\n\n\n\n\n\n\n\n  \n  \n\n\n\n\n\n\n\n\n\n\n\n\n\n\n\n\n\n\n\n\n\n\n\n\n\n\n\n\n\n\n\n\n\n\n\n\n\n\n\n\n\n\n\n\n\n\n  \n\n    \n  \n    \n\n      \n\n      \n        \n          \n        \n        \n\n        \n          \n            \n          \n            \n                \n                \n                \n                \n                \n                \n                \n                \n\n            \n          \n        \n          \n        \n\n        \n      \n        \n      \n\n    \n  \n\n\n  \n\n\n\n\n\n\n\n\n\n\n\n\n\n\n\n\n\n\n\n\n\n\n\n\n\n\n\n\n\n\n\n\n\n\n\n\n\n\n\n\n\n\n\n\n\n  \n\n    \n  \n    \n\n      \n\n      \n        \n          \n        \n        \n\n        \n          \n            \n          \n            \n                \n                \n                \n                \n                \n                \n                \n                \n\n            \n          \n        \n          \n        \n\n        \n      \n        \n      \n\n    \n  \n\n\n  \n\n\n\n\n\n\n\n\n\n\n\n\n\n\n\n\n\n\n\n\n\n\n\n\n\n\n\n\n\n\n\n\n\n\n\n\n\n\n\n\n\n\n\n\n\n  \n\n    \n  \n    \n\n      \n\n      \n        \n          \n        \n        \n\n        \n          \n            \n          \n            \n                \n                \n                \n                \n                \n                \n                \n                \n\n            \n          \n        \n          \n        \n\n        \n      \n        \n      \n\n    \n  \n\n\n  \n\n\n\n\n\n  Copyright Â© 2008-2025 Â Alan Ranger All Rights Reserved.  The Legal Stuff\n\n\n\n\n\n\n\n\n\n\n\n\n\n\n\n\n\n\n\n\n\n  \n  \n\n\n\n\n\n\n\n\n  \n    #block-yui_3_17_2_1_1651564402332_6670 .social-icons-style-border .sqs-svg-icon--wrapper {\n      \n        box-shadow: 0 0 0 2px inset;\n      \n      border: none; \n    }\n  \n  \n    \n      \n        \n          \n          \n        \n      \n    \n      \n        \n          \n          \n        \n      \n    \n      \n        \n          \n          \n        \n      \n    \n      \n        \n          \n          \n        \n      \n    \n      \n        \n          \n          \n        \n      \n    \n  \n\n\n\n\n  (44) 781-7017994 | info@alanranger.com45 Hathaway Road, Coventry, West Midlands, CV4 9HW, United Kingdom\n\n\n\n\n\n\n\n\n\n\n\n\n\n\n\n\n\n\n\n\n\n  \n  \n\n\n\n\n\n  \n\n\n\n\n    \n\n    \n    \n\n    \n\n\n\n\n\n\n\n{\n  \"@context\": \"http://schema.org\",\n  \"@type\": \"Organization\",\n  \"url\": \"https://www.alanranger.com/\",\n  \"logo\": \"https://www.alanranger.com/photography-tuition-icons/6ku1oah790lqdsn401bkwetsaai29o\",\n  \"contactPoint\": [{\n    \"@type\": \"ContactPoint\",\n    \"telephone\": \"+44-781-701-7994\",\n    \"contactType\": \"customer service\"\n  }]\n}\n\n\n\n\n\n(function () {\n  const removeProductSchema = () => {\n    const scripts = document.querySelectorAll('script[type=\"application/ld+json\"]');\n\n    scripts.forEach((script) => {\n      try {\n        const json = JSON.parse(script.textContent);\n\n        if (\n          json['@type'] === 'Product' ||\n          (Array.isArray(json['@type']) && json['@type'].includes('Product'))\n        ) {\n          // Optional safety: only remove if there's no review/aggregateRating\n          const hasReviewData = json.review || json.aggregateRating;\n          if (!hasReviewData) {\n            script.remove();\n          }\n        }\n      } catch (e) {\n        // Ignore malformed scripts\n      }\n    });\n  };\n\n  // Run once on DOM ready\n  document.addEventListener(\"DOMContentLoaded\", removeProductSchema);\n\n  // Run continuously for any future injections\n  const observer = new MutationObserver(() => {\n    removeProductSchema();\n  });\n\n  observer.observe(document.body, {\n    childList: true,\n    subtree: true\n  });\n})();\n\n\n\n\n\n\n\n\n\n\n\n!function(){window.self===window.top||window.top.document.getElementById(\"lazy-summaries-admin\")||function(e,t,s,i,a){if(s.querySelector(\"#\"+t))i&&i(this);else{var n=document.createElement(\"script\");n.src=e+\"?cache=\"+((new Date).getTime()+\"\").substr(0,8),n.id=t,n.onload=function(){a&&this.remove(),i&&i(this)},s.appendChild(n)}}(\"https://assets.squarewebsites.org/lazy-summaries/lazy-summaries-admin.js\",\"lazy-summaries-admin\",window.top.document.getElementsByTagName(\"head\")[0])}();\n\n\n\n\n\n\n window.customRegisterInterestSettings = {\n        '.collection-type-events.view-item': {\n            render: '.eventitem-column-meta',\n            source: '/register-interest',\n            text: 'Register interest',\n            alignment: 'left',\n            size: 'small'\n        },\n   \t\t'.collection-type-products.view-item': {\n            render: '.ProductItem-summary .sqs-add-to-cart-button-wrapper|after',\n            source: '/register-interest-product',\n            text: 'Register interest',\n            alignment: 'left', \n            size: 'small'\n        },\n}\n\n\n\n\n\n\n!(function() {\n    function injectScript(file, id, node) {\n        if (node.querySelector('#' + id)) {\n            return;\n        };\n        var script = document.createElement(\"script\");\n        script.src = file + '?cache=' + (new Date().getTime() + '').substr(0, 13);\n        script.id = id;\n        node.appendChild(script);\n    }\n    if (window.self !== window.top) {\n        document.addEventListener('DOMContentLoaded', function() {\n            setTimeout(function() {\n                injectScript('https://assets.squarewebsites.org/utils/csv-sync/alan-ranger/csv-sync.min.js?time='+(new Date).getTime(), 'csv-collection-sync', window.top.document.getElementsByTagName(\"head\")[0]);\n            }, 200)\n        })\n    }\n})();\n\n\n\ndocument.addEventListener('DOMContentLoaded', function(){\n\tsetTimeout(function(){window.self!==window.top&&(window.top.document.getElementById(\"sqs-admin-hooks\")||window.top.Y.Get.js(\"https://assets.squarewebsites.org/utils/sqs-admin-hooks/sqs-admin-hooks.js?time=\"+(new Date).getTime(),function(e,o){e?console.log(\"Error loading Admin Hooks Script: \"+e[0].error,\"error\"):(console.log(\"Admin Hooks Init\"),o&&o.nodes[0].setAttribute(\"id\",\"sqs-admin-hooks\"))}),window.top.document.getElementById(\"sqs-admin-hooks-date-to-events\")||window.top.Y.Get.js(\"https://assets.squarewebsites.org/utils/sqs-admin-hooks/prepend-date-to-events-descr-hook/date-to-events-descr-hook.js?time=\"+(new Date).getTime(),function(e,o){e?console.log(\"Error loading Admin Hooks Script: \"+e[0].error,\"error\"):(console.log(\"Add date if same description Init\"),o&&o.nodes[0].setAttribute(\"id\",\"sqs-admin-hooks-date-to-events\"))}),window.top.document.getElementById(\"events-collection-sync\")||window.top.Y.Get.js(\"https://assets.squarewebsites.org/utils/events-ical/alanranger-com.min.js?time=\"+(new Date).getTime(),function(e,o){e?console.log(\"Error loading Admin Hooks Script: \"+e[0].error,\"error\"):(console.log(\"Sync Calendar Events\"),o&&o.nodes[0].setAttribute(\"id\",\"events-collection-sync\"))}))}, 200)  \n});\n\n\n\n\n\n\nwindow.collectionsSyncConfig = {\n  \t gallery: {\n            enabled: true,\n            onlyDefined: false,\n       \t\tmoreThan: 1,\n            general : {\n                saveBody: false,\n                saveExcerpt: false,\n                useLZS: false\n            }\n    },\n    events: {\n            enabled: false,\n            onlyDefined: false,\n            general : {\n                saveBody: false,\n                saveExcerpt: false,\n                useLZS: false\n            }\n      },\n      blog: {\n            enabled: false,\n            onlyDefined: false,\n            general : {\n                saveBody: false,\n                saveExcerpt: true,\n                useLZS: true\n            }\n        },\n  \t  products: {\n            enabled: false,\n            onlyDefined: false,\n            general : {\n                saveBody: false,\n                saveExcerpt: true,\n                useLZS: true\n            }\n        }\n  };\n  \n!function(){if(window.self!==window.top){var n,e,o,t,i,c;window.top.document.getElementById(\"collections-index-sync\")||(window.collectionsSyncConfig&&(window.top.collectionsSyncConfig=window.collectionsSyncConfig),n=\"https://assets.squarewebsites.org/utils/collections-indexes/collections-sync.min.js\",e=window.top.document.getElementsByTagName(\"head\")[0],o=\"collections-index-sync\",(c=document.createElement(\"script\")).id=o,c.src=n+\"?cache=\"+((new Date).getTime()+\"\").substr(0,7),c.async=!0,c.onload=function(){i&&this.remove(),t&&t(null,{nodes:[this]})},e.appendChild(c))}}();\n\n\n\n//Filter\nvar monthNames = [\"January\", \"February\", \"March\", \"April\", \"May\", \"June\", \"July\", \"August\", \"September\", \"October\", \"November\", \"December\"];\nvar locations = [\"batsford\",\"coventry\",\"cumbria\",\"devon\",\"dorset\",\"glencoe\",\"hope-valley\",\"kenilworth\",\"lake- district\",\"norfolk\",\"northumbria\",\"solihull\",\"somerset\",\"suffolk\",\"warwickshire\",\"worcestershire\",\"yorkshire\",\"wales\",\"residential\",\"ireland\"];\n\n\n.custom-filter-container.custom-filter-view-dropdowns .customFiltersWrapper .sqs-block {\n  max-width: 33.33%\n  }\n\nwindow.customFilterSettings = {\n    'targets': [{\n            container: '.sqs-events-collection-list, #block-yui_3_17_2_1_1521549855177_44542,#block-yui_3_17_2_1_1564902899455_5204,#collection-53d39321e4b009befdb652c8 .ProductList,#collection-5eb7c3a098232c36f5d347d5 .ProductList',\n            items: '.eventlist-event--upcoming, .summary-item, .ProductList-item',\n            settings: {\n                placeFiltersTo: '.placeFilters',\n                position: 'top',\n                showItemsCount: true,\n                customClasses: '',\n                align: 'center',\n                useHistory: true,\n                updateFilterOptions: {\n                    enabled: true,\n                    nonExistOptions: {\n                        hide: false,\n                        disable: false,\n                        disableHard: false\n                    },\n                    showOptionsCounters: true,\n                    optionsCounterWrap: '- ()',\n                },\n                //keepDropdownsOpen: true,\n                simpleFilter: {\n                    show: {\n                        effect: 'fade',\n                        transitionDuration: 300,\n                        stagger: 30\n                    },\n                    hide: {\n                        effect: 'fade',\n                        transitionDuration: 100,\n                        stagger: 18\n                    }\n                },\n                hooks: {\n                    beforeCreate: function(target) {\n                        if (location.pathname.indexOf('/photography-shop') > -1 || location.pathname.indexOf('/photography-services') > -1) {\n                            target.settings.filter = {\n                                category: false,\n                                tag: false,\n                                items: [{\n                                        name: 'Categories',\n                                        multiple: true,\n                                        getAttr: 'categories'\n                                    },\n                                    {\n                                        name: 'Tag',\n                                        multiple: true,\n                                        notAllowedOptions: locations,\n                                        getAttr: 'tags'\n                                    },\n                                    {\n                                        name: 'Location',\n                                        multiple: false,\n                                        allowedOptions: locations,\n                                        getAttr: 'tags'\n                                    },\n                                ]\n                            }\n                        }\n                        if (location.pathname.indexOf('workshops') > -1) {\n                            target.settings.filter = {\n                                category: false,\n                                tag: false,\n                                items: [{\n                                        name: 'Workshops Location',\n                                        multiple: false,\n                                        getAttr: function(el, data) {\n                                            if (data && data.location && data.location.addressTitle) {\n                                                return data.location.addressTitle;\n                                            }\n                                            return false;\n                                        }\n                                    },\n                                    {\n                                        name: 'Workshops Duration',\n                                        multiple: true,\n                                        getAttr: 'categories'\n                                    }, {\n                                        name: 'Workshops Year',\n                                        multiple: false,\n                                        getAttr: function(it, data) {\n                                            it = it._node || it;\n                                            var time = it.querySelector('[datetime]');\n                                            if (time) {\n                                                time = time.getAttribute('datetime').substr(0, 4);\n                                                return time;\n                                            } else if (data && data.startDate) {\n                                                return new Date(data.startDate).getFullYear()\n                                            }\n                                        }\n                                    },\n                                    {\n                                        name: 'Workshops Month',\n                                        multiple: false,\n                                        allowedOptions: monthNames,\n                                        sort: 'asAllowed',\n                                        getAttr: function(it, data) {\n                                            it = it._node || it;\n                                            var time = it.querySelector('[datetime]');\n                                            if (time) {\n                                                time = new Date(time.getAttribute('datetime')).toLocaleString('default', { month: 'long' });\n                                                return time;\n                                            } else if (data && data.startDate) {\n                                                return new Date(data.startDate).toLocaleString('default', { month: 'long' });\n                                            }\n                                        }\n                                    },\n                                    {\n                                        name: 'Tag',\n                                        multiple: true,\n                                        getAttr: 'tags'\n                                    }\n                                ]\n                            }\n                        }\n                        if (location.pathname.indexOf('course') > -1 || location.pathname.indexOf('classes') > -1) {\n                            target.settings.filter = {\n                                category: false,\n                                tag: false,\n                                items: [{\n                                        name: 'Courses Location',\n                                        multiple: true,\n                                        getAttr: function(el, data) {\n                                            if (data && data.location && data.location.addressTitle) {\n                                                return data.location.addressTitle;\n                                            }\n                                            return false;\n                                        }\n                                    },\n                                    {\n                                        name: 'Courses Categories',\n                                        multiple: true,\n                                        getAttr: 'categories'\n                                    }, {\n                                        name: 'Courses Year',\n                                        multiple: false,\n                                        getAttr: function(it, data) {\n                                            it = it._node || it;\n                                            var time = it.querySelector('[datetime]');\n                                            if (time) {\n                                                time = time.getAttribute('datetime').substr(0, 4);\n                                                return time;\n                                            } else if (data && data.startDate) {\n                                                return new Date(data.startDate).getFullYear()\n                                            }\n                                        }\n                                    }, {\n                                        name: 'Courses Month',\n                                        multiple: false,\n                                        allowedOptions: monthNames,\n                                        sort: 'asAllowed',\n                                        getAttr: function(it, data) {\n                                            it = it._node || it;\n                                            var time = it.querySelector('[datetime]');\n                                            if (time) {\n                                                time = new Date(time.getAttribute('datetime')).toLocaleString('default', { month: 'long' });\n                                                return time;\n                                            } else if (data && data.startDate) {\n                                                return new Date(data.startDate).toLocaleString('default', { month: 'long' });\n                                            }\n                                        }\n                                    }, {\n                                        name: 'Tag',\n                                        multiple: true,\n                                        getAttr: 'tags'\n                                    }\n                                ]\n                            }\n                        }\n                        if (location.pathname.indexOf('/photographic-workshops') > -1) {\n                            target.settings.position = 'top';\n                            //target.settings.customIndexUrl = '/workshops-events-custom-index';\n                        } else if (location.pathname.indexOf('/photography-classes') > -1) {\n                            target.settings.position = 'top';\n                            //target.settings.customIndexUrl = '/classes-events-custom-index';\n                        }\n                    }\n                },\n                sort: {\n                    items: [{\n                            name: 'A-Z',\n                            order: 'asc',\n                            sort: function(el, data) {\n                                if (data) {\n                                    return data.title;\n                                }\n                            }\n                        },\n                        {\n                            name: 'Z-A',\n                            order: 'desc',\n                            sort: function(el, data) {\n                                if (data) {\n                                    return data.title;\n                                }\n                            }\n                        },\n                        {\n                            name: 'Date',\n                            order: 'asc|desc',\n                            sort: function(el, data) {\n                                var result = 1;\n                                if (data && data.id) {\n                                    result = data.startDate;\n                                }\n                                return result;\n                            }\n                        }\n                    ]\n                }\n            }\n        },\n        {\n            container: '#collection-53836c32e4b05b1c55576880 .BlogList, #block-yui_3_17_2_1_1529137402624_4143',\n            items: '.hentry, .summary-item',\n            settings: {\n                //placeFiltersTo: '.collection-header',\n                position: 'top',\n                useSessionCache: false,\n                showItemsCount: true,\n                useHistory: true,\n                //keepDropdownsOpen: true,\n                updateFilterOptions: {\n                    enabled: true,\n                    nonExistOptions: {\n                        hide: false,\n                        disable: false,\n                        disableHard: false\n                    },\n                    showOptionsCounters: true,\n                    optionsCounterWrap: '- ()',\n                },\n                hooks: {\n                    beforeCreate: function(target) {\n                        if (window.top && window.top.Static && window.top.Static.IN_BACKEND) {\n                            target.noNeedCreate = true;\n                        }\n                    },\n                    beforeInit: function(filter) {\n                        //console.log(filter.target.settings)\n                        if (Y.one('body').hasClass('view-list')) {\n                            //filter.target.settings.customIndexUrl = '/blog-blog-custom-index';\n                        }\n                    },\n                    onInit: function(filter) {\n                        filter.target.settings.pagination.loadMoreButton.enabled = false;\n                    }\n                },\n                simpleFilter: {\n                    show: {\n                        effect: 'fade',\n                        transitionDuration: 300,\n                        stagger: 30\n                    },\n                    hide: {\n                        effect: 'fade',\n                        transitionDuration: 100,\n                        stagger: 18\n                    }\n                },\n                sort: {\n                    items: [{\n                        name: 'A-Z',\n                        order: 'asc',\n                        sort: function(el, data) {\n                            var title = '';\n                            if (data) {\n                                title = data.title;\n                            }\n                            return title;\n                        }\n                    }, {\n                        name: 'Z-A',\n                        order: 'desc',\n                        sort: function(el, data) {\n                            var title = '';\n                            if (data) {\n                                title = data.title;\n                            }\n                            return title;\n                        }\n                    }, {\n                        name: 'Date',\n                        order: 'asc|desc',\n                        sort: function(el, data) {\n                            var result = 1;\n                            if (data && data.id) {\n                                result = data.publishOn;\n                            }\n                            return result;\n                        }\n                    }]\n                },\n                pagination: {\n                    enabled: true,\n                    pageSize: 8,\n                    place: \"bottom\",\n                    showPrevNext: { //will show next/prev elements arrows\n                        enabled: true,\n                        //hideItems: true,\n                        next: 'Next', //next link text\n                        prev: 'Prev' //previous link text\n                    },\n                    loadMoreButton: {\n                        enabled: false\n                    }\n                },\n                filter: {\n                    category: false,\n                    tag: false,\n                    items: [{\n                        name: 'Category',\n                        multiple: true,\n                        getAttr: 'categories'\n                    }, {\n                        name: 'Tag',\n                        multiple: true,\n                        getAttr: 'tags'\n                    }]\n                }\n            }\n        }\n    ]\n};\n\n\n\n\n\n\n\n!function(){window.self===window.top||window.document.getElementById(\"sqstp-UI-theme-script\")||function(e,t,s,i,a){if(s.querySelector(\"#\"+t))i&&i(this);else{var n=document.createElement(\"script\");n.src=e+\"?cache=\"+((new Date).getTime()+\"\").substr(0,8),n.async=!0,n.id=t,n.onload=function(){a&&this.remove(),i&&i(this)},s.appendChild(n)}}(\"https://plugins.squarewebsites.org/sqstools-ext/themes/modern.min.js\",\"sqstp-UI-theme-script\",window.document.getElementsByTagName(\"head\")[0])}();\n\n\n\n\n\n\n\n$( \".reading-time\" ).insertBefore( \"h1.BlogItem-title\" );\n\n\n\n\n\n  var scrolled = 400; $(window).scroll(function() {\n    if ( $(window).scrollTop() > scrolled ) {\n      $('a.btt').fadeIn('slow');\n    } else {\n      $('a.btt').fadeOut('slow');\n    }\n  });\n\n\n  $('a.btt').click(function() {\n    $('html, body').animate({ scrollTop: 0 }, 700);\n    return false;\n  });\n\n\n\n\n$(document).ready(function () {\n    // Define the hover timeout duration in milliseconds\n    var hoverTimeoutDuration = 3000; // Example: 3000ms (3 seconds)\n\n    $('.Header-nav-folder-title[href^=\"/mega-\"]').each(function () {\n        var e = $(this).attr(\"href\").slice(6);\n        $(this).parent().addClass(\"mega-menu\");\n        var a = $(this).closest(\"header.Header\");\n        a.append(\"<div id=\" + e + ' class=\"mega-menu-item\"></div>');\n        $(\"#\" + e).load(\"/mega-menu-pages #mega-page-\" + e, function () {\n            window.Squarespace.initializeLayoutBlocks(Y, Y.one(\"#\" + e));\n            var imgs = document.querySelectorAll(\".mega-menu-item img[data-src]\");\n            for (var n = 0; n < imgs.length; n++) {\n                ImageLoader.load(imgs[n], { load: true, fill: true });\n                imgs[n].parentNode.className += \" loaded\";\n            }\n        });\n        var hoverTimeout;\n        // Function to start hover timeout\n        function startHoverTimeout() {\n            clearTimeout(hoverTimeout);\n            hoverTimeout = setTimeout(function () {\n                removeHoverFromAll();\n            }, hoverTimeoutDuration);\n        }\n        // Function to remove hover from all mega menus\n        function removeHoverFromAll() {\n            $('.mega-menu-item').removeClass('hover');\n            $('.mega-menu').removeClass('hover');\n        }\n        // Handle hover on the link's parent\n        $(this).parent().hover(\n            function () {\n                removeHoverFromAll(); // Remove hover from all other mega menus\n                a.find(\"#\" + e).addClass(\"hover\");\n                clearTimeout(hoverTimeout);\n                // Monitor mouse movement to reset hover timeout\n                $(document).on(\"mousemove.megaMenu\", function () {\n                    clearTimeout(hoverTimeout);\n                    startHoverTimeout();\n                });\n            },\n            function () {\n                startHoverTimeout();\n                $(document).off(\"mousemove.megaMenu\");\n            }\n        );\n        // Handle hover on the mega menu content\n        $(\"#\" + e).hover(\n            function () {\n                a.find(\"#\" + e).addClass(\"hover\");\n                clearTimeout(hoverTimeout);\n\n                // Monitor mouse movement to reset hover timeout\n                $(document).on(\"mousemove.megaMenuContent\", function () {\n                    clearTimeout(hoverTimeout);\n                    startHoverTimeout();\n                });\n            },\n            function () {\n                startHoverTimeout();\n                $(document).off(\"mousemove.megaMenuContent\");\n            }\n        );\n        // Detect hover on anything outside the mega menu or its link\n        $(\"body\").on(\"mouseenter\", \"","fitness_level":null,"what_to_bring":null,"course_duration":"in milliseconds","instructor_info":null,"availability_status":null,"meta_description":"The three-week beginners photography classes will teach you the fundamentals of camera operation and composition. Enrol today and start improving your images.","csv_metadata":{"kind":"service","title":null}},{"id":244504,"url":"https://www.alanranger.com/course-finder-photography-classes-near-me","kind":"service","title":"Best Photography Classes Near Me - Course Finder - Coventry","description":"UK Landscape Photography Workshops, Beginners Courses and Private Lessons - Enhance your skill with Alan Ranger Photography - Qualified Tutor and Professional Photographer","date_start":null,"date_end":null,"location":null,"price":null,"price_currency":null,"availability":null,"sku":null,"provider":"Alan Ranger Photography","source_url":"https://www.alanranger.com/course-finder-photography-classes-near-me","raw":{"url":"https://www.alanranger.com","name":"Alan Ranger Photography","@type":"WebSite","image":"//images.squarespace-cdn.com/content/v1/5013f4b2c4aaa4752ac69b17/b859ad2b-1442-4595-b9a4-410c32299bf8/ALAN+RANGER+photography+LOGO+BLACK.+switched+small.png","@context":"http://schema.org","description":"<p class=\"\" style=\"white-space:pre-wrap;\">UK Landscape Photography Workshops,&nbsp;Beginners Courses and Private Lessons - Enhance your skill with Alan Ranger Photography - Qualified Tutor and Professional Photographer</p>"},"entity_hash":"292ec870b9b7cf21f33eb4bfec48fb7975d6ae99","last_seen":"2025-10-29T17:53:24.133+00:00","page_url":"https://www.alanranger.com/course-finder-photography-classes-near-me","norm_title":"best photography classes near me - course finder - coventry","start_date":null,"csv_type":"landing_service_pages","csv_metadata_id":70594,"categories":null,"tags":null,"publish_date":null,"location_name":null,"location_address":"s","excerpt":null,"end_date":null,"start_time":null,"end_time":null,"location_city_state_zip":null,"image_url":null,"json_ld_data":null,"workflow_state":null,"participants":null,"experience_level":null,"equipment_needed":null,"time_schedule":"-15-10","fitness_level":null,"what_to_bring":null,"course_duration":"in milliseconds","instructor_info":null,"availability_status":null,"meta_description":"Learn and master the art of photography with the best photography classes near me!  Course Finder for photography lessons in Coventry or Online - To Suit You","csv_metadata":{"kind":"service","title":null}},{"id":244520,"url":"https://www.alanranger.com/photography-courses-coventry","kind":"service","title":"Top Photography Courses Coventry - Or Online With a Pro","description":"UK Landscape Photography Workshops, Beginners Courses and Private Lessons - Enhance your skill with Alan Ranger Photography - Qualified Tutor and Professional Photographer","date_start":null,"date_end":null,"location":null,"price":null,"price_currency":null,"availability":null,"sku":null,"provider":"Alan Ranger Photography","source_url":"https://www.alanranger.com/photography-courses-coventry","raw":{"url":"https://www.alanranger.com","name":"Alan Ranger Photography","@type":"WebSite","image":"//images.squarespace-cdn.com/content/v1/5013f4b2c4aaa4752ac69b17/b859ad2b-1442-4595-b9a4-410c32299bf8/ALAN+RANGER+photography+LOGO+BLACK.+switched+small.png","@context":"http://schema.org","description":"<p class=\"\" style=\"white-space:pre-wrap;\">UK Landscape Photography Workshops,&nbsp;Beginners Courses and Private Lessons - Enhance your skill with Alan Ranger Photography - Qualified Tutor and Professional Photographer</p>"},"entity_hash":"81de06fe929043cdb8c69fc7542ce355a24599bd","last_seen":"2025-10-29T17:53:23.611+00:00","page_url":"https://www.alanranger.com/photography-courses-coventry","norm_title":"top photography courses coventry - or online with a pro","start_date":null,"csv_type":"landing_service_pages","csv_metadata_id":70593,"categories":null,"tags":null,"publish_date":null,"location_name":null,"location_address":"with a photography workshop.","excerpt":null,"end_date":null,"start_time":null,"end_time":null,"location_city_state_zip":null,"image_url":null,"json_ld_data":null,"workflow_state":null,"participants":null,"experience_level":null,"equipment_needed":null,"time_schedule":"out duration in milliseconds","fitness_level":null,"what_to_bring":null,"course_duration":"in milliseconds","instructor_info":null,"availability_status":null,"meta_description":"Beginner photography courses Coventry or online â?? to suit any level of experience, camera, or budget. Learn photography basics with a professional tutor.","csv_metadata":{"kind":"service","title":null}},{"id":244633,"url":"https://www.alanranger.com/photo-workshops-uk","kind":"service","title":"Photo Workshops UK | Landscape Photography Workshops","description":"PHOTO WORKSHOPS UK | LANDSCAPE PHOTOGRAPHY WORKSHOPS","date_start":null,"date_end":null,"location":null,"price":null,"price_currency":null,"availability":null,"sku":null,"provider":"Alan Ranger Photography","source_url":"https://www.alanranger.com/photo-workshops-uk","raw":{"name":"Alan Ranger Photography","@type":"LocalBusiness","image":"https://static1.squarespace.com/static/5013f4b2c4aaa4752ac69b17/t/6749dba3f5275a74ca88a3bd/1761580471344/","address":"45 Hathaway Road\nCoventry, England, CV4 9HW\nUnited Kingdom","@context":"http://schema.org","openingHours":"Mo 09:00-17:00, Tu 09:00-17:00, We 09:00-17:00, Th 09:00-17:00, Fr 09:00-17:00, Sa 09:00-17:00, Su 09:00-17:00"},"entity_hash":"15a0021851db0fa0832d283957b9b267f6cffadd","last_seen":"2025-10-29T17:53:13.321+00:00","page_url":"https://www.alanranger.com/photo-workshops-uk","norm_title":"photo workshops uk | landscape photography workshops","start_date":null,"csv_type":"landing_service_pages","csv_metadata_id":70631,"categories":null,"tags":null,"publish_date":null,"location_name":null,"location_address":".pathname.indexOf('/photography-services') > -1) {","excerpt":null,"end_date":null,"start_time":null,"end_time":null,"location_city_state_zip":null,"image_url":null,"json_ld_data":null,"workflow_state":null,"participants":null,"experience_level":null,"equipment_needed":null,"time_schedule":"out duration in milliseconds","fitness_level":null,"what_to_bring":null,"course_duration":"in milliseconds","instructor_info":null,"availability_status":null,"meta_description":"Join our immersive landscape photo workshops in the UK to refine your skills and capture stunning natural beauty. Learn from expert professional photographers.","csv_metadata":{"kind":"service","title":null}}],"events":[],"products":[],"articles":[]},"debugInfo":{"intent":"rag_first","classification":"direct_answer","confidence":0.7,"entityTitles":[],"approach":"rag_first_hybrid","debugLogs":["DEPLOYMENT TEST V2 - This should appear in response","Answer length: 149","Answer preview: I offer a range of photography services â?? includin...","Chunks found: 0","Entities found: 0"]}}
